Workbook
Name Confidence: Key!$A$15:$A$17
Name EvalScore: Key!$A$22:$A$26
Name RiskRelevant: Key!$A$31:$A$33
Name Typology: Key!$A$6:$A$10

Sheet Contents
F4: Full list of CCRA3 risk and opportunity scores
F7: This spreadsheet summarises all of the magnitude and urgency scores, by UK nation, for each climate change risk and opportunity assessed in the CCRA3 Technical Report. Also shown are the Committee's scores against the criteria used to determine the top eight priority risk areas for action in the next two years, outlined in the CCRA3 Advice Report.
F17: Source: https://www.theccc.org.uk/publication/independent-assessment-of-uk-climate-risk/#supporting-data-charts

Sheet Full scores
D1: Magnitude Score
A2: Risk or Opportunity Descriptor (BOLD = Committee priority risks) | B2: Chapter | C2: Nation | D2: Present Day | E2: 2050, 2° | F2: 2050, 4° | G2: 2080, 2° | H2: 2080, 4° | I2: Adaptation Score | J2: Urgency Score | K2: UK-wide Urgency score for Advice Report | L2: CCC Progress Scores for England (2019)* | M2: CCC Progress Scores for Scotland (2019)* | N2: Key policy opportunities in the next 2 years (UK wide, Committee View)
A3: N1 Risks to terrestrial species and habitats from changing climatic conditions and extreme events, including temperature change, water scarcity, wildfire, flooding, wind, and altered hydrology (including water scarcity, flooding and saline intrusion) | B3: 3 | C3: England | D3: High | E3: High | F3: High | G3: High | H3: High | I3: Partially | J3: More action needed | K3: More action needed | L3: Low (3) | M3: Medium (Amber) | N3: High (Environment and nature recovery policy reform)
B4: 3 | C4: Scotland | D4: High | E4: High | F4: High | G4: High | H4: High | I4: Partially | J4: More action needed
B5: 3 | C5: Wales | D5: High | E5: High | F5: High | G5: High | H5: High | I5: Partially | J5: More action needed
B6: 3 | C6: Northern Ireland | D6: High | E6: High | F6: High | G6: High | H6: High | I6: Partially | J6: More action needed
A7: N2 Risks to terrestrial species and habitats from pests, pathogens and invasive species | B7: 3 | C7: England | D7: Medium | E7: High | F7: High | G7: High | H7: High | I7: Partially | J7: More action needed | K7: More action needed | L7: Low (3) | M7: Medium (Amber) | N7: High (Environment and nature recovery policy reform)
B8: 3 | C8: Scotland | D8: Medium | E8: Medium | F8: Medium | G8: Medium | H8: High | I8: Partially | J8: More action needed
B9: 3 | C9: Wales | D9: Medium | E9: Medium | F9: Medium | G9: Medium | H9: High | I9: Partially | J9: More action needed
B10: 3 | C10: Northern Ireland | D10: Medium | E10: Medium | F10: Medium | G10: Medium | H10: High | I10: Partially | J10: More action needed
A11: N3 Opportunities from new species colonisations in terrestrial habitats | B11: 3 | C11: England | D11: Medium | E11: Medium | F11: Medium | G11: Medium | H11: High | I11: No | J11: Further investigation | K11: Further Investigation | L11: Low (3) | M11: N/A | N11: Low (No key policies looking at opportunities in the next 2 years)
B12: 3 | C12: Scotland | D12: Medium | E12: Medium | F12: Medium | G12: Medium | H12: High | I12: No | J12: Further investigation
B13: 3 | C13: Wales | D13: Medium | E13: Medium | F13: Medium | G13: Medium | H13: High | I13: No | J13: Further investigation
B14: 3 | C14: Northern Ireland | D14: Medium | E14: Medium | F14: Medium | G14: Medium | H14: High | I14: No | J14: Further investigation
A15: N4 Risk to soils from changing climatic conditions, including seasonal aridity and wetness. | B15: 3 | C15: England | D15: Medium | E15: High | F15: High | G15: High | H15: High | I15: Very partially | J15: More action needed | K15: More action needed | L15: N/A | M15: Low (Red) | N15: High (New land management and rural support schemes)
B16: 3 | C16: Scotland | D16: Medium | E16: High | F16: High | G16: High | H16: High | I16: Very partially | J16: More action needed
B17: 3 | C17: Wales | D17: Medium | E17: High | F17: High | G17: High | H17: High | I17: Very partially | J17: More action needed
B18: 3 | C18: Northern Ireland | D18: Medium | E18: High | F18: High | G18: High | H18: High | I18: Very partially | J18: More action needed
A19: N5 Risks and opportunities for natural carbon stores, carbon sequestration and GHG emissions from changing climatic conditions, including temperature change and water scarcity | B19: 3 | C19: England | D19: Medium | E19: High | F19: High | G19: High | H19: High | I19: No | J19: More action needed | K19: More action needed | L19: N/A | M19: Low (Red) | N19: High (Net Zero, new land management and rural support schemes, Environment and nature recovery policy)
B20: 3 | C20: Scotland | D20: Medium | E20: High | F20: High | G20: High | H20: High | I20: No | J20: More action needed
B21: 3 | C21: Wales | D21: Medium | E21: High | F21: High | G21: High | H21: High | I21: No | J21: More action needed
B22: 3 | C22: Northern Ireland | D22: Medium | E22: High | F22: High | G22: High | H22: High | I22: No | J22: More action needed
A23: N6 Risks to and opportunities for agricultural and forestry productivity from extreme events and changing climatic conditions (including temperature change, water scarcity, wildfire, flooding, coastal erosion, wind and saline intrusion). | B23: 3 | C23: England | D23: Medium | E23: High | F23: High | G23: High | H23: High | I23: Very partially | J23: More action needed | K23: More action needed | L23: Low (1) | M23: Low (Red) | N23: High (Net Zero, new land management and rural support schemes, Environment and nature recovery policy)
B24: 3 | C24: Scotland | D24: Medium | E24: High | F24: High | G24: High | H24: High | I24: Very partially | J24: More action needed
B25: 3 | C25: Wales | D25: Medium | E25: High | F25: High | G25: High | H25: High | I25: Very partially | J25: More action needed
B26: 3 | C26: Northern Ireland | D26: Medium | E26: High | F26: High | G26: High | H26: High | I26: No | J26: More action needed
A27: N7 Risks to agriculture from pests, pathogens and invasive species | B27: 3 | C27: England | D27: Medium | E27: High | F27: High | G27: High | H27: High | I27: Partially | J27: More action needed | K27: More action needed | L27: Low (1) | M27: Low (Red) | N27: High (New land management and rural support schemes, naure recovery policy reform)
B28: 3 | C28: Scotland | D28: Medium | E28: High | F28: High | G28: High | H28: High | I28: Partially | J28: More action needed
B29: 3 | C29: Wales | D29: Medium | E29: High | F29: High | G29: High | H29: High | I29: Partially | J29: More action needed
B30: 3 | C30: Northern Ireland | D30: Medium | E30: High | F30: High | G30: High | H30: High | I30: Partially | J30: More action needed
A31: N8 Risks to forestry from pests, pathogens and invasive species | B31: 3 | C31: England | D31: Medium | E31: High | F31: High | G31: High | H31: High | I31: Partially | J31: More action needed | K31: More action needed | L31: Medium (5) | M31: Medium (Amber) | N31: High (New land management and rural support schemes, nature recovery policy reform)
B32: 3 | C32: Scotland | D32: Medium | E32: High | F32: High | G32: High | H32: High | I32: Partially | J32: More action needed
B33: 3 | C33: Wales | D33: Medium | E33: High | F33: High | G33: High | H33: High | I33: Partially | J33: More action needed
B34: 3 | C34: Northern Ireland | D34: Medium | E34: High | F34: High | G34: High | H34: High | I34: Partially | J34: More action needed
A35: N9 Opportunities for agricultural and forestry productivity from new/alternative species becoming suitable. | B35: 3 | C35: England | D35: Medium | E35: High | F35: High | G35: High | H35: High | I35: No | J35: Further investigation | K35: Further Investigation | L35: Low (1) | M35: N/A | N35: Low (No key policies looking at opportunities in the next two years)
B36: 3 | C36: Scotland | D36: Medium | E36: High | F36: High | G36: High | H36: High | I36: No | J36: Further investigation
B37: 3 | C37: Wales | D37: Medium | E37: High | F37: High | G37: High | H37: High | I37: No | J37: Further investigation
B38: 3 | C38: Northern Ireland | D38: Medium | E38: High | F38: High | G38: High | H38: High | I38: No | J38: Further investigation
A39: N10 Risks to aquifers and agricultural land from sea level rise, saltwater intrusion | B39: 3 | C39: England | D39: Low | E39: Low | F39: Low | G39: Low | H39: Unknown | I39: Yes | J39: Further investigation | K39: Further Investigation | L39: N/A | M39: N/A | N39: Low (no key policies in the next two years)
B40: 3 | C40: Scotland | D40: Low | E40: Low | F40: Low | G40: Low | H40: Low | I40: Yes | J40: Watching brief
B41: 3 | C41: Wales | D41: Low | E41: Low | F41: Low | G41: Low | H41: Unknown | I41: Yes | J41: Further investigation
B42: 3 | C42: Northern Ireland | D42: Low | E42: Low | F42: Low | G42: Low | H42: Low | I42: Yes | J42: Watching brief
A43: N11 Risks to freshwater species and habitats from changing climatic conditions and extreme events, including higher water temperatures, flooding, water scarcity and phenological shifts. | B43: 3 | C43: England | D43: Medium | E43: Medium | F43: Medium | G43: Medium | H43: High | I43: Partially | J43: More action needed | K43: More action needed | L43: Medium (5) | M43: Low (Red) | N43: High (Replacement of the Water Framework Directive, nature recovery policies)
B44: 3 | C44: Scotland | D44: Medium | E44: Medium | F44: Medium | G44: Medium | H44: High | I44: Partially | J44: More action needed
B45: 3 | C45: Wales | D45: Medium | E45: Medium | F45: Medium | G45: Medium | H45: High | I45: Partially | J45: More action needed
B46: 3 | C46: Northern Ireland | D46: Medium | E46: Medium | F46: Medium | G46: Medium | H46: High | I46: Partially | J46: More action needed
A47: N12 Risks to freshwater species and habitats from pests, pathogens and invasive species | B47: 3 | C47: England | D47: High | E47: High | F47: High | G47: High | H47: High | I47: Partially | J47: More action needed | K47: More action needed | L47: Medium (5) | M47: Low (Red) | N47: High (Replacement of the Water Framework Directive, nature recovery policies)
B48: 3 | C48: Scotland | D48: Medium | E48: Medium | F48: Medium | G48: Medium | H48: Medium | I48: Partially | J48: More action needed
B49: 3 | C49: Wales | D49: Medium | E49: Medium | F49: Medium | G49: Medium | H49: Medium | I49: Partially | J49: More action needed
B50: 3 | C50: Northern Ireland | D50: Medium | E50: Medium | F50: Medium | G50: Medium | H50: Medium | I50: Partially | J50: More action needed
A51: N13 Opportunities to freshwater species and habitats from new species colonisations | B51: 3 | C51: England | D51: Low | E51: Low | F51: Low | G51: Low | H51: Low | I51: Partially | J51: Sustain current action | K51: Sustain current action | L51: Medium (5) | M51: N/A | N51: Low (No key policies looking at opportunities in the next two years)
B52: 3 | C52: Scotland | D52: Low | E52: Low | F52: Low | G52: Low | H52: Low | I52: Partially | J52: Sustain current action
B53: 3 | C53: Wales | D53: Low | E53: Low | F53: Low | G53: Low | H53: Low | I53: Partially | J53: Sustain current action
B54: 3 | C54: Northern Ireland | D54: Low | E54: Low | F54: Low | G54: Low | H54: Low | I54: Partially | J54: Sustain current action
A55: N14 Risks to marine species, habitats and fisheries from changing climatic conditions, including ocean acidification and higher water temperatures. | B55: 3 | C55: England | D55: Medium | E55: High | F55: High | G55: High | H55: High | I55: Partially | J55: More action needed | K55: More action needed | L55: Medium (5) | M55: Medium (Amber) | N55: Medium (implementation of MPA network and new fisheries policy)
B56: 3 | C56: Scotland | D56: Medium | E56: High | F56: High | G56: High | H56: High | I56: Partially | J56: More action needed
B57: 3 | C57: Wales | D57: Medium | E57: High | F57: High | G57: High | H57: High | I57: Partially | J57: More action needed
B58: 3 | C58: Northern Ireland | D58: Medium | E58: High | F58: High | G58: High | H58: High | I58: Partially | J58: More action needed
A59: N15 Opportunities to marine species, habitats and fisheries from changing climatic conditions | B59: 3 | C59: England | D59: Medium | E59: High | F59: High | G59: High | H59: High | I59: No | J59: Further investigation | K59: Further Investigation | L59: Medium (5) | M59: N/A | N59: Medium (implementation of MPA network and new fisheries policy)
B60: 3 | C60: Scotland | D60: Medium | E60: High | F60: High | G60: High | H60: High | I60: No | J60: Further investigation
B61: 3 | C61: Wales | D61: Medium | E61: High | F61: High | G61: High | H61: High | I61: No | J61: Further investigation
B62: 3 | C62: UK | D62: Medium | E62: High | F62: High | G62: High | H62: High | I62: No | J62: Further investigation
A63: N16 Risks to marine species and habitats from pests, pathogens and invasive species | B63: 3 | C63: England | D63: Medium | E63: High | F63: High | G63: High | H63: High | I63: Partially | J63: More action needed | K63: More action needed | L63: Medium (5) | M63: Medium (Amber) | N63: Medium (implementation of MPA network and new fisheries policy)
B64: 3 | C64: Scotland | D64: Medium | E64: High | F64: High | G64: High | H64: High | I64: Partially | J64: More action needed
B65: 3 | C65: Wales | D65: Medium | E65: High | F65: High | G65: High | H65: High | I65: Partially | J65: More action needed
B66: 3 | C66: Northern Ireland | D66: Medium | E66: High | F66: High | G66: High | H66: High | I66: Partially | J66: More action needed
A67: N17 Risks and opportunities to coastal species and habitats due to coastal flooding, erosion and climate factors | B67: 3 | C67: England | D67: Medium | E67: High | F67: High | G67: High | H67: High | I67: Partially | J67: More action needed | K67: More action needed | L67: N/A | M67: Medium (Amber) | N67: Medium (New or reviewed coasyal policies and implementation of renewed flood policies)
B68: 3 | C68: Scotland | D68: Medium | E68: High | F68: High | G68: High | H68: High | I68: Partially | J68: More action needed
B69: 3 | C69: Wales | D69: Medium | E69: High | F69: High | G69: High | H69: High | I69: Partially | J69: More action needed
B70: 3 | C70: Northern Ireland | D70: Medium | E70: High | F70: High | G70: High | H70: High | I70: Partially | J70: More action needed
A71: N18 Risks and opportunities from climate change to landscape character | B71: 3 | C71: England | D71: Medium | E71: High | F71: High | G71: High | H71: High | I71: Very partially | J71: Further investigation | K71: Further Investigation | L71: N/A | M71: N/A | N71: Low (no key policies in the next two years)
B72: 3 | C72: Scotland | D72: Medium | E72: High | F72: High | G72: High | H72: High | I72: Very partially | J72: Further investigation
B73: 3 | C73: Wales | D73: Medium | E73: High | F73: High | G73: High | H73: High | I73: Partially | J73: Further investigation
B74: 3 | C74: Northern Ireland | D74: Medium | E74: High | F74: High | G74: High | H74: High | I74: No | J74: Further investigation
A75: I1 Risks to infrastructure networks (water, energy, transport, ICT) from cascading failures | B75: 4 | C75: England | D75: High | E75: High | F75: High | G75: High | H75: High | I75: Partially | J75: More action needed | K75: More action needed | L75: Low (1) | M75: Medium (Amber) | N75: High (review of national risk assessments)
B76: 4 | C76: Scotland | D76: High | E76: High | F76: High | G76: High | H76: High | I76: Partially | J76: More action needed
B77: 4 | C77: Wales | D77: High | E77: High | F77: High | G77: High | H77: High | I77: Partially | J77: More action needed
B78: 4 | C78: Northern Ireland | D78: High | E78: High | F78: High | G78: High | H78: High | I78: Partially | J78: More action needed
A79: I2 Risks to infrastructure services from river, surface water and groundwater flooding | B79: 4 | C79: England | D79: High | E79: High | F79: High | G79: High | H79: High | I79: Partially | J79: More action needed | K79: More action needed | L79: N/A | M79: Medium (Amber) | N79: Medium (implementation of flood policies)
B80: 4 | C80: Scotland | D80: High | E80: High | F80: High | G80: High | H80: High | I80: Partially | J80: More action needed
B81: 4 | C81: Wales | D81: High | E81: High | F81: High | G81: High | H81: High | I81: Partially | J81: More action needed
B82: 4 | C82: Northern Ireland | D82: High | E82: High | F82: High | G82: High | H82: High | I82: Partially | J82: More action needed
A83: I3 Risks to infrastructure services from coastal flooding and erosion | B83: 4 | C83: England | D83: Medium | E83: Medium | F83: Medium | G83: Medium | H83: Medium | I83: Partially | J83: Further investigation | K83: Further Investigation | L83: N/A | M83: Medium (Amber) | N83: High (New or reviewed coasyal policies and implementation of renewed flood policies)
B84: 4 | C84: Scotland | D84: Medium | E84: Medium | F84: Medium | G84: Medium | H84: Medium | I84: Partially | J84: Further investigation
B85: 4 | C85: Wales | D85: Medium | E85: Medium | F85: Medium | G85: Medium | H85: Medium | I85: Partially | J85: Further investigation
B86: 4 | C86: Northern Ireland | D86: Medium | E86: Medium | F86: Medium | G86: Medium | H86: Medium | I86: Partially | J86: Further investigation
A87: I4 Risks to bridges and pipelines from flooding and erosion | B87: 4 | C87: England | D87: Medium | E87: Medium | F87: Medium | G87: Medium | H87: Medium | I87: Partially | J87: Further investigation | K87: Further Investigation | L87: N/A | M87: N/A | N87: Medium (implementation of flood policies)
B88: 4 | C88: Scotland | D88: Medium | E88: Medium | F88: Medium | G88: Medium | H88: Medium | I88: Partially | J88: Further investigation
B89: 4 | C89: Wales | D89: Medium | E89: Medium | F89: Medium | G89: Medium | H89: Medium | I89: Partially | J89: Further investigation
B90: 4 | C90: Northern Ireland | D90: Medium | E90: Medium | F90: Medium | G90: Medium | H90: Medium | I90: Partially | J90: Further investigation
A91: I5 Risks to transport networks from slope and embankment failure | B91: 4 | C91: England | D91: Medium | E91: Medium | F91: Medium | G91: Medium | H91: Medium | I91: Partially | J91: More action needed | K91: More action needed | L91: Medium (5) | M91: High (Green) | N91: High (Network Rail review of vulnerability of the rail network following the Stonehaven crash)
B92: 4 | C92: Scotland | D92: Medium | E92: Medium | F92: Medium | G92: Medium | H92: Medium | I92: Partially | J92: More action needed
B93: 4 | C93: Wales | D93: Medium | E93: Medium | F93: Medium | G93: Medium | H93: Medium | I93: Partially | J93: More action needed
B94: 4 | C94: Northern Ireland | D94: Medium | E94: Medium | F94: Medium | G94: Medium | H94: Medium | I94: Partially | J94: More action needed
A95: I6 Risks to hydroelectric generation from low or high river flows | B95: 4 | C95: England | D95: Low | E95: Medium | F95: Medium | G95: Medium | H95: Medium | I95: Partially | J95: Further investigation | K95: Further Investigation | L95: N/A | M95: N/A | N95: Medium (reviews underway of environmental permitting)
B96: 4 | C96: Scotland | D96: Low | E96: Medium | F96: Medium | G96: Medium | H96: Medium | I96: Partially | J96: Further investigation
B97: 4 | C97: Wales | D97: Low | E97: Medium | F97: Medium | G97: Medium | H97: Medium | I97: Partially | J97: Further investigation
B98: 4 | C98: Northern Ireland | D98: Low | E98: Low | F98: Low | G98: Low | H98: Low | I98: Partially | J98: Watching brief
A99: I7 Risks to subterranean and surface infrastructure from subsidence | B99: 4 | C99: England | D99: Low | E99: Medium | F99: Medium | G99: Medium | H99: Medium | I99: Partially | J99: Further investigation | K99: Further Investigation | L99: N/A | M99: N/A | N99: Low (no key policies in the next two years)
B100: 4 | C100: Scotland | D100: Low | E100: Medium | F100: Medium | G100: Medium | H100: Medium | I100: Partially | J100: Further investigation
...

Sheet Contents Page
B2: About this document
B4: This document was produced by RSK ADAS Limited ('ADAS') on behalf of the Climate Change Committee.
B5: Please refer to the report which accompanies this spreadsheet for further information.
B7: Contents
B9: This document has eight tabs which contain the following information:
B11: Tab | C11: Description
B12: Contents Page | C12: Background information and contents of this document.
B13: CCRA3 Risks | C13: Summary table of the CCRA3 risks and content from the Technical Report for 'Benefits of further adaptation action in the next five years'.
B14: CCRA3 actions for NAP3 | C14: Evaluation of the extent to which NAP3 addressed the adaptation actions recommended in CCRA3.
B15: PR23 Recommendations | C15: Outlines the CCC recommendations to Government in the 2023 Progress Report to Parliament and the Government's response to these.
B16: Graphs | C16: Summary visualisations to illustrate evaluation findings.
B17: No. actions per risk | C17: Provides a summary of the number of inferred adaptation actions that were provided in the CCRA3 Technical Report, per risk.
B18: Glossary | C18: Summary of acronyms used within the Government's Response to the CCC Recommendations.
B19: Key | C19: Key to typologies and evaluation scores used in the assessment.
B21: Data sources
B23: The source of data for each column in each tab is listed within the note for each column title.
B25: Summary of data sources used within this document:
B27: Document | C27: Available from:
B28: CCC (2021) Advice to Government - Full Risk Table - Scoring and Priorities | C28: https://www.theccc.org.uk/wp-content/uploads/2021/07/Independent-Assessment-of-UK-Climate-Risk-Advice-to-Government-Full-Risk-Table-Scoring-and-Priorities.xlsx
B29: CCC (2023) Progress Report to Parliament | C29: https://www.theccc.org.uk/publication/progress-in-adapting-to-climate-change-2023-report-to-parliament/
B30: Defra (2023) The Third National Adaptation Programme (NAP3) and the Fourth Strategy for Climate Adaptation Reporting | C30: https://assets.publishing.service.gov.uk/media/64ba74102059dc00125d27a7/The_Third_National_Adaptation_Programme.pdf
B31: Defra (2023) Annex 1: Climate risks and opportunities | C31: https://assets.publishing.service.gov.uk/media/64b52a430ea2cb001315e3b7/NAP3_Annex_1_Climate_risks_and_opportunities.pdf
B32: Defra (2023) Government response to the Climate Change Committee 2023 report to Parliament – progress in adapting to climate change | C32: https://www.gov.uk/government/publications/government-response-to-the-climate-change-committee-2023-adaptation-progress-report/government-response-to-the-climate-change-committee-2023-report-to-parliament-progress-in-adapting-to-climate-change
B33: UK Climate Risk (2021) Independent Assessment (CCRA3) Technical Report | C33: https://www.ukclimaterisk.org/publications/technical-report-ccra3-ia/

Sheet CCRA3 Risks
A1: ID# | B1: Risk or Opportunity Descriptor (BOLD = Committee priority risks) | C1: Committee Priority risk | D1: Chapter | E1: Benefits of further adaptation action in the next five years (CCRA3 section X.X.3) | F1: Indicative costs and benefits of additional adaptation (CCRA3 section X.X.3.1) | G1: Nation | H1: England Magnitude Score Present Day | I1: England Magnitude Score 2050, 2° | J1: England Magnitude Score 2050, 4° | K1: England Magnitude Score 2080, 2° | L1: England Magnitude Score 2080, 4° | M1: England Adaptation Score | N1: England Urgency Score | O1: UK-wide Urgency score for Advice Report | P1: CCC Progress Scores for England (2019)* | Q1: CCC Progress Scores for Scotland (2019)* | R1: Key policy opportunities in the next 2 years (UK wide, Committee View) | S1: Nature | T1: Working land and seas | U1: Food security | V1: Water supply | W1: Energy | X1: Telecommunications & ICT | Y1: Transport | Z1: Towns and Cities | AA1: Buildings | AB1: Health | AC1: Community preparedness and response | AD1: Business | AE1: Finance | AF1: Interdependencies | AG1: Not captured
A2: B01 | B2: B1 Risks to business sites from flooding | C2: No | D2: 6 | E2: Given our assessment above, our view is that there will be significant benefits from further action in the next five years from low-regret actions to improve the evidence base and provide further awareness raising, advice and support to businesses to improve their resilience to flooding. Quantifying risks and impacts is difficult, particularly for individual business sectors, where data is often commercially sensitive. However, Sayers et al. (2020) report that if further adaptation measures are taken, in addition to what is currently planned then the UK-wide expected annual damages for non-residential properties could decrease by up to 21% increase by 2080. Results are calculated under the Enhanced Whole System model. Businesses could also make use of the flood forecasting and warning services provided by the Environment Agency, Natural Resources Wales and SEPA, in conjunction with the Met Office, to plan for and respond to flooding in their areas. In terms of government support, stakeholder engagement indicates that investing in 3D interactive models for commercial properties would be beneficial for data collection. Whilst this will require significant government investment, insurance companies alone are unlikely to bear the upfront costs. It is likely that improving the uptake of property flood protection by businesses will have significant benefits in the next five years, though further data are required to understand this and the current level of uptake specifically in the context of SMEs. | F2: The overall benefits of further investment in flood management for commercial property through the reduction in expected annual damages are estimated by Sayers et al. (2020). This study does not estimate the costs of these measures, and thus does not undertake a cost-benefit analysis, but the literature in general reports high benefit to cost ratios from such investment (Rojas et al., 2013: Ward et al., 2017). There are some low regret activities where Government can act to enhance adaptation in the private sector. The uptake of adaptation measures by businesses is relatively low, with small businesses particularly at risk: only a quarter of businesses with fewer than 10 employees have continuity plans for extreme weather (in GOS and Foresight, 2017). This despite the fact that such plans are a cost-effective adaptation measure: around four-fifths of businesses with continuity plans in place report that the benefits of having a plan exceed the costs of producing one. There is, therefore, a role for raising awareness on climate risks (flood alerts) and providing relevant information and response planning. There is now a reasonable evidence base on the costs and benefits of property resilience and resistance measures for households (Environment Agency, 2015; Wood Plc 2019). These found that a number of flood resilience and resistance measures could be considered no-regret adaptation measures (i.e., a benefit to cost ratio of greater than one in cases where there is a greater than 1% chance of Annual Exceedance Probability, AEP). In general, this literature reports that all measures are more expensive if retrofitted rather than installed in new builds. For resistance measures, the difference between costs of retrofitting vs. incorporating into new builds are more modest. However, the applicability of each of these measures depends on the type of flooding (recurrence and depth), as this alters the relative cost-effectiveness (and benefit to cost ratio). While there is less data on the costs and benefits of similar measures for commercial properties, it is likely that similar findings of low-regret adaptation opportunities apply. There is also some wider literature on the benefits of blue and green infrastructure in alleviating direct and indirect damages from flooding to industry and infrastructure, using the city of Newcastle as a case study (Blue-Green Cities Project, 2016). This assessed the benefits of sustainable urban drainage on water flow, sediment dynamics and flood risk in fluvial systems. Given the residual damage costs even with current flood management policy (Sayers et al., 2020) this is clearly an area where there are benefits of future action, and in many cases these benefits are projected to outweigh the costs. | G2: England | H2: High | I2: High | J2: High | K2: High | L2: High | M2: Partially | N2: More action needed | O2: More action needed | P2: Medium (5) | Q2: Medium (Amber) | R2: Medium (implementation of flood policies) | AD2: Y
A3: B02 | B3: B2 Risks to business locations and infrastructure from coastal change from erosion, flooding and extreme weather events | C3: No | D3: 6 | E3: 6.3.3.1 Additional planned adaptation that would address the adaptation shortfall? (B2) Adaptation actions in the next five years have the potential to enable business opportunities to be created from climate change impacts on the coast, and possibly to avoid further losses. Opportunities exist for coastal businesses from the re-designation of management policy in coastal areas (e.g., from defended to undefended). Depending on the designation, the opportunity exists for businesses to bid for coastal partnership funding to redevelop the coastal area. There is also the potential for business opportunities to emerge from habitat creation, or new approaches to construction to enable communities to ‘live with rising seas’. Coastal properties could also be purchased and repurposed to generate income, e.g., wind farms, temporary holiday lets (Coastal Partnership East, 2019) Overall there is a lack of research and evidence in this area. There is also a business opportunity for new designs/building structures, such as portable beach homes which can be lifted out of harm’s way, providing low impact low risk solutions for future sea-side tourism. Sayers et al. (2020) report that if further adaptation measures are taken, in addition to what is currently planned (see Figure 6.8), then the UK-wide expected annual damages for non-residential properties will increase by 5% in 2050 and increase by 27% by 2080 compared to present day levels of expected damage in the 2°C warming scenario and increase by 27% by 2050 and 58% by 2080 in the 4°C warming scenario. It should be noted however that the Sayers report did not cover coastal erosion and was concluded before the publication of the National Flood and Coastal Erosion Risk Management Strategy (Environment Agency, 2020b) and the Flood and Coastal Erosion Risk Management Strategy Policy Statement (HM Government, 2020). Results are calculated under the Enhanced Whole System model, with results by country for both the 2°C and 4°C warming scenarios presented in Figure 6.9. As can be seen, additional adaptation would significantly decrease expected annual damages to non-residential properties in Scotland and Wales. It is important to note that adaptation solutions do not apply across the board and are context specific. For example, increased coastal protection may work in one community in response to sea level rise, but relocation may be more feasible for a different community. Figure 6.9 Further adaptation: Percentage change in expected annual damages to non-residential properties for scenarios of global warming reaching 2°C and 4°C in the late 21st Century - coastal flooding, direct, £millions (%). Source: Sayers et al. (2020) Some other potential benefits of further adaptation in the next five years include increased transparency about protection levels and limits to avoid false sense of security; public engagement in developing future visions for coastal communities; or investments in community resilience. According to the CCC coastal change report (CCC, 2018), one of the main factors that could aid implementation of more proactive, and cost-effective relocation of coastal properties and assets at risk (i.e., ‘move the risk’), is a change in government policy, associated funding prioritisation and outcome measures. It should be noted that this report was published before the publication of the National Flood and Coastal Erosion Risk Management Strategy (Environment Agency, 2020b) and the Flood and Coastal Erosion Risk Management Strategy Policy Statement (HM Government, 2020). These changes could facilitate the ability to plan and implement the management approaches identified for each of the coastal areas around the UK, particularly those at high risk. More active business engagement with existing resources available for coastal development in ‘at risk’ areas would likely increase adaptation, for example through FCERM partnership funding and Grant-in-Aid support. New guidance was released on the Grant-in-Aid scheme in 2020 to help businesses identify what resources are available for adaptation and what additional funds would need to be secured. Transparency around planned coastal designation changes (from defended to undefended) could support more active adaptation. Providing clearer communication and more transparency should help businesses to avoid a false sense of security and to allow them to plan for future climate risks. Given that the Shoreline Management Plans are non-statutory policy documents, they can only inform wider strategic planning. The Plans also do not consider the full scale of future climate change risks (e.g., high++ scenarios) and do not set out the more radical adaptation responses that could manage those risks. The CO-designing the Assessment of Climate Change costs (COACCH) research report (COACCH, 2019a) notes that the costs of adaptation vary significantly with the level of future climate change, the level of acceptable risk protection and the framework of analysis (protection versus economic efficiency). Recognising and working with uncertainty as part of integrated and sustainable policies requires an iterative and flexible approach that positions coastal change adaptation within a broader integrated coastal-zone management policy framework. For example, new coastal development visions should be fully aligned with climate futures. The COACCH Report, which also includes an analysis of adaptation in the UK, reinforces the message that the most appropriate response to sea-level rise for coastal areas is a combination of adaptation to deal with the inevitable rise and mitigation to limit the long-term rise to a manageable level (COACCH, 2019a) Climate change forms part of a range of risks and uncertainties most industries routinely face. For example, seafood sector adaptations could include much closer science-industry collaboration and engaged research in the short term; and a move towards a more robust and strategic fisheries knowledge base in the medium term (Garrett et al., 2015). More work is needed to identify business opportunities in high-risk coastal areas, including better understanding of funding resources, clearer communication and a realistic appraisal of the risks and opportunities for businesses at the coast. More research is required to understand the costs and benefits of different adaptation responses to loss of coastal locations for businesses and infrastructure. Further analysis is required on how risk will change in the future and how this should inform decisions on a national outcome and strategy for flood risk alleviation. The National Infrastructure Commission (NIC) proposed the adoption or exploration of national minimum standards of resilience (NIC, 2018) though as yet this has not been adopted by government. Defra (2018) indicate that local businesses (potentially with assets at risk) are often an important source of partnership funding for larger schemes. This must be capitalised during stakeholder engagement. Moreover, critical business infrastructure like transport or ports, as well as industry critical business infrastructure such as industrial plants (i.e. chemical and petrochemical plants, oil refineries, gas processing plants) and factories (i.e., food processing facilities, pharmaceutical manufacturing), which are typically located on the coast or on tidal rivers / estuaries out of necessity for process feedstock import and finished product export can be given a level of protected status when it comes to government flood risk management, as suggested by ABP (2016). The Institute of Mechanical Engineers suggests that this infrastructure is vital to national economic prosperity and growth as well as local economies and communities (IMechE 2019). Our view is that for some sectors and some parts of the UK, guidance on appropriate adaptation in the short term has been identified (e.g., fisheries in England and Scotland), however in other parts of the UK, more investigation is needed to identify pathways of action, for example in Northern Ireland. Since CCRA2, the policy environment has changed, creating new opportunities for businesses and creating more adaptation guidance and support in all four of the UK countries. In the longer term, actions relating to the institutional arrangements for adaptation could be considered. For example, governance of fisheries (of both regulated and non-regulated species) could be adapted in the short, medium and long term as there will likely be a need for flexible institutional arrangements to respond to climate change. The finance sector can encourage adaptation by policyholders through incentivisation; Governments and insurers can play a key role by providing further financial incentives for adaptation; for instance, they can set policy premiums at a level that more closely reflects the risk to which individual properties are exposed. However, some elements of coastal change such as erosion are excluded from insurance. If adaptation measures are not implemented, the insurance that currently exists will become more expensive and less available. At present, flood insurance for businesses is being driven by private insurance companies, with low government scope or obligation to pay compensation (Sayers et al., 2020). This issue merits further investigations given lack of consideration in current flooding evidence reports (Sayers et al., 2020). | F3: The overall benefits of further investment in coastal flood management for commercial property – and the reduction in expected annual damages – are shown in Figure 6.8 and 6.9 The Sayers et al. (2020) study does not estimate the costs of these measures, and thus does not undertake a cost-benefit analysis. In general terms, the literature reports that coastal adaptation is an extremely cost-effective response, significantly reducing residual damage costs to very low levels (Hinkel et al., 2014), however, in rural areas, such measures often have benefit-cost ratios lower than one. A new approach to investigating the wider dividends of adaptation and resilience interventions is demonstrated by Roezer et al., 2021 for the case of Felixstowe on the East Coast of England, where increased coastal protection from the new flood defences stimulated new investments in the property sector including the creation of new jobs and a boost to local businesses through increase in visitors, of which the local authority attributed around 50% to the new flood protection scheme. The assessment and retrospective evaluation of additional resilience dividends by the Coastal Partnership East (CPE), a group of local authorities, as part of the monitoring and valuation stage was done to support the business case for similar projects and future interventions. (Roezer et al., 2021). | G3: England | H3: Medium | I3: High | J3: High | K3: High | L3: High | M3: Partially | N3: More action needed | O3: More action needed | P3: Medium (5) | Q3: Medium (Amber) | R3: Medium (New or reviewed coastal policies and implementation of renewed flood policies) | AD3: Y
A4: B03 | B4: B3 Risks to businesses from water scarcity | C4: No | D4: 6 | E4: 6.4.3.1 Additional planned adaptation that would address the adaptation shortfall? (B3) Watkiss et al. (2019) found that there are high benefits (although also high potential costs) of further action to reduce the risk of water scarcity. The costs and benefits do not just fall under the category of businesses but are part of a larger picture of action to reduce demand and increase supply across business, infrastructure, and households, with an aim of protecting and enhancing the natural environment. Currently, there is a lack of incentives for water companies to help reduce commercial water use, and reduction efforts have been left to the retail market, unlike in the domestic sector. Further understanding of sectoral usage is required for this (Ofwat and Environment Agency, 2020). Water UK (2016) has estimated that a ‘twin track’ approach of demand management coupled with appropriate development of new resources and potential transfers is the most suitable strategy for providing drought resilience in the future. They estimated that total costs per annum for all potential future scenarios to maintain resilience at existing levels in England and Wales are between £50 million and £500 million per annum in demand management and new water resource options. If resilience to ‘severe drought’ is adopted, this increases to between £60 million and £600 million and for resilience to extreme drought (beyond the 1 in 100-year event) to between £80 million and £800 million per annum. In England a number of the policy measures that Defra consulted on in 2019 to reduce personal water use, for example, could also help increase business water efficiency and reduce water and energy use. Prime among these is water efficiency labelling of water using products linked to minimum standards for new build and retrofits which would realise significant benefits both for domestic and business water users (Defra, 2019). One idea MOSL (2020) are looking at is to map out their data on business water users and overlay that data set with maps of current or future water stress areas the Environment Agency hold. This would help identify where efforts to reduce business use could be prioritised and what types of businesses/sectors could be targeted. Ideally this can be used to inform next round of water resource plans so a further adaptation action for the next 5 years. High consumption businesses can be incentivized monetarily, for instance through cheaper rates for businesses if they don’t consume in the summer when peak demand is hard to manage. Some of the key business benefits of handling water stewardship effectively include (WWF and M&S, 2017) reduced water related business risk, increased drought preparedness, reduced carbon emissions from supply and heating of water, continuity of supply from sourcing locations for retail businesses, cost savings associated with water efficiency, strong engagement with the local community, and reputational benefits. WWF suggests there will be significant benefits to the UK from taking the following further actions (WWF, 2015): the UK government should share the evidence base, for example the Environment Agency’s water and agriculture monitoring, widely with business and explore opportunities to help businesses identify key hotspots (e.g., showing impacts related to product type). To ensure there is a strong framework for the sustainable management of water WWF suggests more efforts to bring non-compliant farmers in England into compliance and ensuring basic legislation is sufficient to support further achievement of good heath, as defined by the Water Framework Directive. Other suggestions focus on reforming abstraction licensing to ensure environmental needs are met as a function of every licence and that abstraction charges encourage efficient use; and continuing investment in the Catchment Based Approach including by exploring ways to encourage private sector support and funding (WWF 2015). Stakeholder discussions as part of the UKCCRA3 stakeholder engagement indicate that a consistent methodology for measuring & reporting water use for products (water foot printing) is to be encouraged. There would be benefits to looking at whole life cycle approach to measuring water usage and make sure embedded water is fully taken into account in such reporting. The long-term trends and pinch point analysis would provide useful tools for industry and Government to show where to focus efforts for either improved water efficiency of business or increased resilience of supply. The retail market could help to create incentives for businesses to become more water efficient but has so far only had a limited impact. The opening of the retail market for water offers multiple benefits for businesses but the potential effect on water efficiency is uncertain. The CEO Water Mandate’s Corporate Water Disclosure Guidelines offer a common approach to disclosure. They put forward metrics that can begin to harmonize practice and also provide guidance for defining what to report. These Guidelines have the potential to drive convergence and harmonization with respect to how companies report their water management practices while helping to minimize reporting burdens, thus allowing companies to allocate more time and resources to actively manage water. The list of endorsing companies as well as reports on their progress can be found online and are updated regularly (CEO Water Mandate, 2014). | F4: As highlighted above, there are studies which have considered the overall costs and benefits of national level action to reduce the risk of water scarcity. There are also a complementary set of demand side measures that can be introduced by businesses, many of which are no-regret and low-regret. As a general rule of thumb, reductions of 30% in water bills are usually achievable at little or no cost for sites that have not previously tried to save water, and as much as 50%, or more, if projects with capital investment payback periods of up to two years are included (WRAP, 2005). There are detailed cost-effectiveness assessments of measures for industrial sites, with indications of costs and payback periods. However, as highlighted above, there remain important barriers to address to encourage the uptake of such measures, which includes a role for government to raise awareness and create appropriate incentives. There is a strong case for Governments to consider adopting consistent national minimum levels of resilience, recognizing that there are significant issues to address, including inter-regional and inter-generational fairness. The investment needed to increase resilience appears relatively modest compared with the cost of drought. A twin-track approach that includes supply enhancement, with associated transfers, as well as demand management, is the most appropriate strategic mix for the future. There is a case for a national level adaptive plan that supports ongoing water company plans and balances risks against opportunities to defer costs. See also Chapter 4 (Jaroszweski, Wood and Chapman, 2021) and Chapter 5 (Kovats and Brisley, 2021). | G4: England | H4: Low | I4: Medium | J4: Medium | K4: Medium | L4: High | M4: Partially | N4: Further investigation | O4: Further Investigation | P4: Medium (5) | Q4: High (Green) | R4: Low (no key policies in the next two years) | AD4: Y
A5: B04 | B5: B4 Risks to finance, investment and insurance including access to capital for businesses | C5: No | D5: 6 | E5: 6.5.3.1 Additional planned adaptation that would address the adaptation shortfall? (B4) There have been significant shifts in assessing, disclosing and analysing climate risks and more is expected in light of expected shifts from voluntary to mandatory action driven by regulators. However, translating this increased risk knowledge into action and drawing conclusions is equally important, and the extent to which companies will successfully do this remains unclear. While it is clear that the extent of physical risks is currently low and expected to become significant in the longer-term there are clear dangers in considering physical risks ‘as under control’: lock-ins for example in terms of real-estate investment but also lack of insurance uptake, particularly on business continuity. Since CCRA2, changes have mainly been made in climate risk regulation and reporting as opposed to changing capital flows. Moreover, given the tightening climate policy landscape, there are significant lock-in effects if there is no substantial redirection of financial flows. Whilst banking and insurance sectors have effectively responded to current extreme weather events, the increase in magnitude and frequency of impacts in the future means the likelihood of “unhedgeable risk” is higher – straining the insurance sector. Given that financial risks are still not integrated within firm operating models or in financial markets as a whole, there are still significant systemic risks (Mandel et al, 2020). Whilst companies have started adopting TCFD recommendations, identifying climate risks is only the first step. TCFD’s most recent status update report acknowledges that there needs to be a better understanding of how disclosing climate-related financial information is changing corporate strategies on adaptation, and how investors are using the disclosed information to inform their decisions (Power et.al. 2020; TCFD, 2020). CISL (2019) recommends early action in addressing risks to accessing finance and investment is predicted to lead to higher economic growth rates and returns over the long run when compared to scenarios of inaction. Moreover, further investment is required to scale-up pre-existing resilience solutions and technologies (NDF, 2020). The following are a number of key areas that could be addressed in the next five years: ● Requirements imposed on banks and insurers: Based on Pillar 2 of the supervision of institutions’ risk management, regulators could prescribe additional capital on a case-by-case basis, for instance if a financial institution does not adequately monitor and manage climate-related risks. This would first require new expectations to be set in this regard (BIS, 2020). Further action is required by banks in order to meet Bank of England stress testing requirements. Currently there is very little data and organisational capacity to collect information in the aftermath of disasters (e.g. collection strategies after a flood) (Deloitte, 2020). Banks require data (e.g. location of collateral, exposure to carbon intensive industries etc.) in order to better respond to physical and transition risk. For instance, green vs brown exposure and funding of carbon intensive industries is not being considered (Deloitte, 2020). In scenario analysis, the banking sector needs to adopt and consider much longer timelines than it is used to at present (Deloitte, 2020). ● Broadening scope of existing regulations: The current review of climate stress testing by the Bank of England’s PRA (Bank of England, 2019) provides an opportunity to broaden the scope, identify limitations and important constraints, and support companies in their internal interpretation of scenario analysis results. Whilst the stress-testing is intermittently paused due to COVID-19 (IMF, 2020), this could be a step towards encouraging more scenario-based analysis among financial institutions on a regular basis. In the future, regulators could make it mandatory for financial institutions to stress-test their portfolios against a common set of scenarios. (UNEP-FI / Vivid 2019). Mandatory disclosure is also called for by the IMF (2020). Stakeholder engagement suggested there is insurers support for this, with mandatory disclosure of methodologies and impact recommended. ● Insurability: Given rising uncertainty, Mckinsey (2020) recommend risk-sharing agreements between private and public financial institutions, similar to that seen in flood insurance, in order to meet financing gaps. Given that Flood Re is only available to non-businesses, there should be increased incentives for resilience to businesses. This also directly relates to uptake of insurance. Whilst there is an increase in the uptake of climate related insurance products, products need to be more streamlined, made cost-effective and user-friendly to promote further business uptake (Marsh & McLennan Companies 2018). Insurance can be used to incentivise risk-reducing behaviour, for example by rewarding adaptation measures like hardening of physical assets (Mckinsey, 2020). As highlighted in section 7.10 of Chapter 7 (Challinor and Benton, 2021), this uptake in insurance from the UK’s expertise within re-insurance companies and catastrophe risk modelling organisations is an opportunity for the UK insurance market to grow. ● Disclosing and reporting: Further standardisation and clarification on scenario analysis models are required so comparisons can be made. Moreover, inclusion of additional asset classes will make these models more useful for investors (Mercer, 2019). Standardisation can occur through investor collaboration facilitated by government-led initiatives (UNEP-FI, 2019). Scenario analyses currently do not cover the entire value-chain of businesses and further integration is required between transition and physical risks as well as the link between micro and macroeconomic impacts (UNEP-FI, 2019). Further developments of dashboards and monitoring mechanisms are required to capture “investors and markets channelling finance to climate solutions” and change in financial flows are a response to climate risk (CPI, 2019). Additionally, more bottom-up information, such as KPIs from businesses, need to be incorporated in scenario analyses which have predominantly been top-down. A push for disclosure of granular, asset level data is required from businesses for scenario analysis to be successful (UNEP-FI, 2019). ● Financial and physical risk metrics: It is important to recognise the interplay of financial metrics and physical risk metrics: for example, the credit risk of a bank from increasing physical risk can be low if it does not lend to companies in high-risk areas. Finity (2019) show it is important to distinguish between risk to individual financial companies versus wider financial implications. Unless physical risk is being reduced through more adaptation investment and action, those damages will occur and have financial implications. ● Incorporating risk reduction and data into insurance requirements: One proposed solution relating to the short-term valuation cycle issue is that policymakers and insurers could incorporate risk reduction and adaptation measures into insurance requirements (CISL, 2019). Other options include making sure risk data is populated across a wide range of sectors and groups, including a focus both on the current symptoms and problems and the underlying causes incorporated into day-to-day decision-making. Surminski (2017) showed that it is essential to first address the use of data and transparency around risk levels. This foundational trust and understanding is needed to reduce the risk of the private sector withdrawing altogether from the flood insurance space or consumers not being able or willing to pay high premiums (Surminski, 2017). ● Financing adaptation: Where funding pools exist, like bond markets, better education is required to match counterparties (Marsh & McLennan Companies 2018). Further research is required in the area of new products, such as resilience bonds, which would use premium discounts for long-term planning, such as investment in sustainable infrastructure, in the catastrophe bond market. Synergies between climate financing and risk management strategies in the banking and insurance sector must be further explored (Marsh & McLennan Companies 2018). ● More collaboration between different parts of the financial system: Capital providers to investors and lenders will likely want to understand how such location decisions, intermediated by insurance availability (discussed above) and adaptation action (discussed below), are taking account of the physical risks of climate change. To the extent that investors and lenders do alter location decisions, it is projected to be much less disruptive to the real economy if this happens over a long period of time rather than as an abrupt response to one or a series of particular events (CISL, 2019). However, investors and lenders, combined with policymakers, may find it easier to take a longer-term perspective. They could work in concert with insurers to encourage the uptake of adaptation measures, for instance, by making both loans and insurance contingent on the installation of relevant adaptation measures (CISL, 2019). This is in line with UNEP-FI (2018) who encourage improved collaboration between banks, borrowers, governments and the insurance industry, and would increase the quality of forward-looking disclosures. | F5: It is difficult to estimate the potential costs and benefits of adaptation. However, what is clear is that the potential risks to the financial markets from climate change are extremely large, and because of the role of UK financial services, very large for the UK. EIU (2015) estimated the value at risk, as a result of climate change, to the total global stock of manageable assets (currently $143 trillion) as $4.2 trillion (mean expected losses, discounted in present value terms) between now and the end of the century, and still half this even under a pathway to 2°C global warming by 2100. | G5: England | H5: Medium | I5: Medium | J5: High | K5: Medium | L5: High | M5: Partially | N5: Sustain current action | O5: Sustain current action | P5: Medium (5) | Q5: N/A | R5: High (TCFD reporting, focus on finance for COP26) | AE5: Y
A6: B05 | B6: B5 Risks to business from reduced employee productivity due to infrastructure disruption and higher temperatures in working environments | C6: Yes | D6: 6 | E6: 6.6.3.1 Additional planned adaptation that would address the adaptation shortfall? (B5) The CCRA2 Evidence Report (Surminski et al., 2016) outlined a need to further research and understanding of the key interdependencies between business and infrastructure, the types of employment at greatest risk and the effectiveness of planned or autonomous adaptation. Collecting business continuity information on productivity and extreme weather is critical to understanding this risk better. Adaptation reporting could help to increase uptake and encourage businesses to prioritise this risk, but a requirement would be needed to include productivity risks in reports, which is challenging given the current voluntary approach to reporting adopted by the UK Government. Very few studies have looked at either the risk or adaptation underway in the UK, suggesting further investigation is required across the UK to better quantify both the scale of the problem, and the benefits of implementing measures to address it both in current and future climates. In particular, evidence for future risk from reduced employee productivity is limited. 6.6.3.2 Indicative costs and benefits of further adaptation action (B5) There is some information on various adaptation options to reduce heat in commercial buildings and also linkages to the information available for domestic buildings (see the discussion of low and no-regret options for risk H1, Chapter 5: Kovats and Brisley, 2021). Day et al. (2019) assessed 17 adaptation measures (drawn from a longer list of over 30), including both solutions for indoor and outdoor work, to address higher base temperatures as well short-term temperature peaks. The authors estimated the ‘potential scale of impact’ as well as the ‘feasibility’ of the measures. This also includes analysis of which actions can be taken forward by the private sector, by government and by individuals. The study also considers the economic costs of each adaptation measure including direct financial costs of implementing the measure, and a range of ‘indirect’ costs. Costa et al. (2016) also estimated averted losses from alternative adaptation measures for three case study cities (Antwerp, Bilbao, and London) for a warm year at the end of the century (2081-2100). These studies identify a range of low and no-regret adaptation actions. Some opportunities for labour productivity adaptation are identified such as transition to new ways of working (remote working, flexible working) and low carbon and energy efficiency buildings to maintain employee productivity (ILO, 2019, Day et al., 2019). These behavioural changes have been tested and employed by various businesses with the onset of the COVID-19 pandemic, but longer-term behavioural change is yet to be seen. Moreover, there are occupational and sectoral divergences in the uptake of new ways of working, with some professions lending themselves better to flexible working than others. Increasing collaboration and strengthening governance in this space may also deliver benefits in the next five years. Better collaboration between business, building owners, government and infrastructure operators could help facilitate adaptation. These efforts could replicate the engagement and collaborations seen in the flooding space and be linked to net-zero initiatives, recognizing that heat poses challenges for reaching net-zero. With regards to nature-based solutions as a potential adaptation response to extreme heat, there is emerging literature estimating the climate benefits of urban natural capital at the UK scale (Eftec et al., 2018). This valuation methodology provides estimates of temperature reduction in city areas and benefits, which feed into the Natural Capital Accounts by ONS (ONS 2018). Although experimental in nature, these estimates give a sense of the scale of benefits (particularly in terms of avoided loss of productivity) and how these might rise over time with an increasing frequency of ‘hot’ days. For instance, in 2017, the annual benefits of cooling from green and blue space in urban areas was estimated at £244m, with London dominating the benefits (reflecting the climate of London, the scale of its economy and the unusually large area of green space for such a big city). The ONS 2018 assessment uses analysis from Eftec (Defra, 2018a) and is based on Costa et al.’s (2016). However, increasing the area of large natural spaces in urban areas, in response to rising climate risks, appears challenging, not least because of the opportunity cost of land. Initiatives led by the private sector such as ‘Living roofs and walls – from policy to practice’ aim to address these issues. | F6: N/A | G6: England | H6: Low | I6: Medium | J6: Medium | K6: Medium | L6: High | M6: Partially | N6: Further investigation | O6: Further Investigation | P6: Low (2) | Q6: Medium (Amber) | R6: High (Reviews of building regulations and planning, Net Zero) | AD6: Y
A7: B06 | B7: B6 Risks to business from disruption to supply chains and distribution networks | C7: Yes | D7: 6 | E7: 6.7.3.1 Additional planned adaptation that would address the adaptation shortfall? (B6) The majority of further actions involve capacity building, institutional changes, or the development of new strategies, technologies or ways of working, which will take time to develop, test and implement. Therefore, there is a benefit to putting these in place within the next five years even where the climate-related risks are not immediate. Indeed, the BCI recommends an offensive rather than a defensive approach (Marsh & McLennan Companies 2018), while McKinsey (2020) finds significant potential for many industries to adapt in the next decade. For example, in the case of rare earth metals they estimated that 50-80% of risk could be eliminated if adaptation measures were implemented (McKinsey 2020). Furthermore, many of the actions can be seen as ‘no-regrets’ options business continuity planning that builds resilience in supply chains or improves the quality of business relationships offers immediate benefits. Strategies that businesses could take to further build resilience include: ● Product diversification or geographical diversifying (WWF, 2018). ● Scenario analysis to ensure plans are robust under different plausible outcomes by explicitly defining and separating external scenarios from internal plans (Marsh & McLennan Companies, 2018). ● Ensuring risks are incorporated into risk registers and management programmes so that optimal resources and opportunities to improve corporate performance and earnings can be identified (BCI, 2018a). ● Intensification in the use of storage facilities (COACCH, 2019). ● More ‘bridging’ actions, that is, inclusion of supply chain partners in risk assessments, planning and communications (Crisis Control, 2017). Given the post-EU exit uncertainty due to changing supply chains Tim et al. (2019) recommend more investment in the agricultural systems of source countries in order to minimise climate risk. And the World Business Council for Sustainable Development (Land workers' Alliance, 2019) recommends adopting a circular model for resilience, with shocks and stressors in the food, agriculture and forestry sector, being met with adaptation response and transformation of existing business models and supply chains. ● Making more use of technology to improve traceability mechanisms (YGCP, 2020) and to predict, monitor, record, measure or report supply chain risks and communicate with suppliers. For example, using automated communication and notification systems, BCM platforms, incident management platforms or social media monitoring (favoured by SMEs) (BCI, 2018b; BCI, 2019a). ● Expanding firm level insurance coverage of physical risks to supply chains, including by use of new products such as non-damage supply chain insurance plans and parametric insurance (for example, with pay-outs based on a drought duration index or rainfall data rather than losses) or captive insurance solutions. The latter can improve climate resilience by strategically funding risk exposures, preparing for a worst-case scenario in the face of increasing frequencies and by accessing reinsurance markets and alternative capital markets to fund less predictable risks (Marsh & McLennan Companies, 2018; BCI, 2019a). There are roles for both the public and private sector in driving resilience through supporting or/ incentivising their own supply chains to implement adaptation measures by: ● Requiring physical risk disclosures and setting contractual arrangements that take adaptation into account (UNEP-FI and Acclimatise, 2018). ● Using resilience criteria with choosing suppliers as part of procurement processes (Crisis Control, 2017). For public sector procurement, the Public Services (Social Value) Act provides a potential tool by requiring commissioners of public services to think about how they can also secure wider social, economic and environmental benefits. (Source: CCRA3 Stakeholder Event, February 2020) ● Helping suppliers reduce their own risks (Crisis Control, 2017). For example, the water stewardship approach provides companies with a means of committing resource and using influence to support good water practices in areas of weak governance. ● Promoting business continuity, with a particular focus on strategies that achieve multiple goals including resilience and sustainability for which there may be market failures. For example, distributed manufacturing, seasonal produce and local sourcing have a role to play in achieving both sustainability and resilience goals (Colwill et al., 2016). There is also a role for government in capacity building and setting the right institutional environment (COACCH, 2019), such as by: ● Promoting the establishment of binding supply chain due diligence legislation on a national level while ensuring international alignment (YGCP, 2020). ● Promoting the coherent use and development of modern traceability technology, namely blockchain (YGCP, 2020). ● Supporting improved climate and location-based information and integration with other types of information (UNEP-FI and Acclimatise, 2018). Taking into account all three steps of the urgency assessment we conclude that more action is needed, but with a low certainty in the evidence, which is skewed towards larger companies, the food sector and self-reporting. The reliance on overseas markets means UK supply chains are exposed to climate impacts abroad with exposure increasing due to climate change. While some action has been taken by businesses and others on supply chain resilience and there are opportunities from advances in technologies, there are many barriers to adaptation. It is unclear how effective current and planned actions will be in managing climate or weather-related disruption specifically. The COVID-19 crisis may lead to companies and entire industries rethinking their global supply chain model. This presents an opportunity for step change in government action to facilitate this and achieve multiple benefits. This is applicable across all DAs, but more work is needed to understand regional differences. The evidence base is strongest for England, followed by Scotland, with less for NI and Wales. | F7: There are some aspects of climate change risks and responses that have been quantified for food supply chain resilience. Even here, however, there is little information on the associated costs and benefits (in aggregate), as identified by recent review of food supply chains and adaptation (Watkiss et al., 2019), though it did identify potential adaptation measures and their potential (qualitative) benefits and costs, indicating net beneficial further actions exist. | G7: England | H7: Medium | I7: Unknown | J7: Unknown | K7: Unknown | L7: Unknown | M7: Partially | N7: More action needed | O7: More action needed | P7: Low (2) | Q7: Medium (Amber) | R7: High (TCFD reporting, possible increased focus on supply chain resilience post-Covid) | U7: Y | AD7: Y
A8: B07 | B8: B7 Opportunities for business from changes in demand for goods and services | C8: No | D8: 6 | E8: 6.8.3.1 Additional planned adaptation that would address the adaptation shortfall? (B7) Identifying opportunities in increased demand for goods and services, such as climate advisory or adaptation products are important to make a business case for climate adaptation in the next five years. This requires greater evidence, such as case-studies, and further investigation into emerging sectors. Currently, there is low confidence in information available, and some opportunities, such as in the retail sector, require further investigation. Business capacity needs to be assessed post-COVID-19, to determine whether these opportunities will be realised, and what barriers exist. Across the country there appear significant opportunities linked to retro-fitting of the building stock. Most initiatives such as the smart energy programme, are currently aimed at achieving low-carbon targets. Using these investments to also increase climate resilience of buildings would bring employment and profitability to construction and advisory services. Opportunities in some sectors, like increased use of air conditioning due to hot weather, must be reassessed, especially in view of lock-ins, maladaptation, threshold effects and associated transition risks, such as changes in energy policy. In view of COVID-19, a greater emphasis must be placed on transformational adaptation, and the opportunities this brings (Tompkins et al., 2010; UKCIP, 2015). Changes in demand for goods and services must be viewed in tandem with sectoral change, technological advances and the institutional and labour-market changes. The emphasis placed on ‘green stimulus’ presents government-backed demand in sectors. Whilst the UK currently ranks highly in the ‘Green Stimulus Index’, this is largely due to underlying environmental performance. There are also some new opportunities in transport, industry and energy (Vivid Economics and Finance for Biodiversity Initiative, 2020). Opportunities for financial investments have also been identified. However, it remains to be seen whether there is industry-wide demand for adaptation solutions (Vivid Economics and Finance for Biodiversity Initiative, 2020). Further investigation is required into the regulatory and institutional networks that can facilitate these opportunities. The LSE Climate Risk Business Survey (2020) found that respondents engaging with suppliers, regulators, banks, investors and insurers are undertaking a more diverse range of adaptation actions. It remains to be seen whether recommendations for investment in adaptation technologies presented by the CCC (2020) or expert calls for a Sustainable Recovery Alliance (Allan et al., 2020; Hepburn et al., 2020) proposed to the Government will occur and produce benefits. | F8: Given the range of sectors and opportunities it is difficult to identify specific costs and benefits of adaptation. There are sectors where analysis has been undertaken (e.g. Watkiss et al., 2019 for wine) which indicates that under a scenario where wine growers were able to realise the benefits of climate change due to better information (and appropriate response), and at the same time introduce adaptation measures to address potential variability risks, there would be very large economic benefits, and a high benefit to cost ratio. | G8: England | H8: Low | I8: Medium | J8: Medium | K8: Medium | L8: Medium | M8: Partially | N8: Further investigation | O8: Further Investigation | P8: Low (2) | Q8: High (Green) | R8: Low (No key policies looking at opportunities in the next two years) | AD8: Y
A9: H01 | B9: H1 Risks to health and wellbeing from high temperatures | C9: Yes | D9: 5 | E9: 5.2.3.1 Additional planned adaptation that would address the adaptation shortfall (H1) There are benefits of adaptation in the next five years, particularly to avoid lock with housing and urban designs that are not adapted to future temperature extremes. The requirements for housing to be suitable for future climates require coordinated action and optimisation of outcomes against the range of objectives (climate and non-climate related). The evidence indicates that currently decarbonisation (Net Zero) and adaptation policies and strategies are not well aligned (CCC, 2019d). The EAC (Environmental Audit Committee, 2018a) highlighted the need for cross-departmental policy and it is important that overheating risks are addressed in all types of buildings where people spend significant time. The CCC have made a number of recommendations to Government in relation to housing across the UK (CCC, 2019a): • A legal standard or regulation should be introduced to address overheating risk for current and future climates at design stage of new-build homes or renovations. • Ensure that passive cooling measures are prioritised over mechanical cooling where a risk of overheating is identified. • Further action is needed to better understand when overheating occurs in existing homes in order for passive cooling measures and behaviour change programmes to be targeted effectively. Climate change presents several risks for housing alongside overheating, such as flooding and damp risks. It is likely to be more effective and less expensive (especially for social housing landlords) to address these risks at the same time through retrofitting to address overheating. In our view, there is a need for increased guidance and incentives to address overheating in existing homes through retrofitting, given the lack of information available on what measures are effective for householders (CCC, 2019a; Power et al., 2020). Based on the assessment above, our view is that continuous preventative planning to include long term risks would have benefits in the next five years, including consideration of longer term risks within current emergency preparedness planning. Air conditioning (or mechanical space cooling) has additional benefits and potential harms, in addition to the increased household energy costs (see Risk H6 for a more detailed discussion). There may also be other health dis-benefits from air conditioning; there is some evidence regarding the negative effects of using air conditioning, including the understanding that it can limit acclimatisation (Yu et al., 2012). The presence of air conditioning in housing is currently low in the UK (at about 3% of homes) (Khare et al., 2015). Although uptake may increase autonomously in the future, relying on air conditioning to deal with the risk is a potentially maladaptive solution, and it expels waste heat into the environment – thereby enhancing the urban heat island effect. | F9: The quantified benefits and costs of addressing overheating in buildings involves a range of assumptions about mortality risks associated with overheating. Several studies have compared the costs of mechanical vs. passive methods of space cooling in new houses and retrofits (Grant et al., 2011; Frontier Economics, Irbaris LLP and Ecofys, 2013; Adaptation Sub-Committee, 2014; Li et al., 2019; Wood Plc, 2019). These generally report positive benefit to cost ratios or high cost-effectiveness (£ / % reduction in temperature). This indicates the potential for low regret options but also that there is a need (and opportunity) to address further risks in climate smart design to address lock-in risks and co-benefits. This is a complex area to assess costs (to households) given the multiple co-benefits and potential harms for each housing intervention. No-cost options to manage overheating can be effective to some extent, such as utilising increased natural ventilation (opening windows), using existing blinds and curtains during the day to limit heat gain and changing behaviours. Shading is the most cost-effective option for cooling houses (Wood Plc, 2019). Many low-carbon retrofit options share commonalities with adaptation options and so could potentially share the cost and reduce overall costs. There is also analysis of the benefits and costs of heatwave warning systems. Several studies report high benefit to cost ratios for future heat related mortality (Bouwer et al., 2018; Chiabai et al., 2018) including analysis in the UK for the Heat Health Watch System (HHWS) (Hunt et al., 2017). Benefit to cost ratios are high and increase significantly under climate change. The studies assume that the cost of operating the warning system increases under future climate change, but this may not be the case as the health system response may become more efficient, and the costs to the provider (e.g. the Met Office) are assumed to be fixed. As discussed above, the heat alert systems alone do not fully manage the health risk in the population (Watkiss et al., 2019b). | G9: England | H9: High | I9: High | J9: High | K9: High | L9: High | M9: Partially | N9: More action needed | O9: More action needed | P9: Low (2) | Q9: Medium (Amber) | R9: High (Reviews of building regulations and planning, Net Zero) | Z9: Y | AA9: Y | AB9: Y | AC9: Y
A10: H02 | B10: H2 Opportunities for health and wellbeing from higher temperatures | C10: No | D10: 5 | E10: There are clearly benefits from further investment in strategies to increase physical activity and mental health – and the opportunities for outdoor recreation and active travel. There is little information on the costs and benefits involved in additional interventions to help address opportunities for health and well-being, but there is likely to be the potential for low-regret and low-cost interventions to help raise awareness and ensure opportunities are fully realised. There are well established interventions for public health communication and awareness raising although these have largely been targeted at impacts rather than opportunities in the health and adaptation domain to date. Interventions to enhance opportunities could lead to large economic benefits (Hunt et al., 2017) in terms of societal welfare from three components: (i) lower resource costs, i.e. avoided medical treatment costs; (ii) increased opportunity costs from gains in productivity; and (iii) the avoided dis-utility, i.e. pain or suffering, concern and inconvenience to family and others. A no-regret option would be to investigate these potential benefits and look at the possible interventions to help deliver these. | F10: N/A | G10: England | H10: Low | I10: Low | J10: Low | K10: Medium | L10: Medium | M10: Partially | N10: Further investigation | O10: Further Investigation | P10: N/A | Q10: N/A | R10: Low (No key policies looking at opportunities in the next two years) | AB10: Y | AC10: Y
A11: H03 | B11: H3 Risks to people, communities and buildings from flooding | C11: No | D11: 5 | E11: The types of adaptation measures required and the impacts on managing flood risk vary spatially. Figure 5.9 shows how the increase in risk is more sensitive to the adaptation choice than others. This highlights the limited opportunities for enhanced adaptation in some of the small local authorities and those in coastal settings with limited available land outside of the flood plain for new development. The difference between the alternative adaptation portfolios is also particularly marked for some local authorities, suggesting that enhanced adaptation efforts in these areas will be required to manage future risk. Importantly even with enhanced adaptation, residual risk is not inconsequential, requiring sustained action to minimise the impacts of this risk and potentially requiring transformational solutions such as relocation. Figure 5.9. Drivers of change in future Expected Annual Damages (total) by 2080s. Reproduced from Sayers et al.(2020a) Whilst Defra’s Policy Statement, the English and Welsh national FCERM strategies and the proposed strategy for Scotland promote many elements of the enhanced whole system adaptation scenario, the challenge now is to move from strategic aspirations to delivery on the ground. Specific areas where our assessment suggests additional action is needed in the next five years are summarised below: • The shift from protection to embracing a range of measures that achieve resilience is supported across the UK. Articulating and promoting exactly what this means in practice is likely to be challenging. Whilst there is a substantial body of research being conducted to inform and facilitate this change in approach, working across the UK nations and widely sharing outcomes from case study examples and initiatives such as the Flood and Coastal Resilience Innovation programme in England is needed to enable a more integrated approach. This could also generate fuller public engagement about the respective roles of different actors in reducing risk and taking adaptive measures, as well as help to promote community level responses that could build resilience. • There is an economic case for increasing investment in socially vulnerable areas, and whilst current funding approaches prioritise support for deprived communities in England, Scotland and Wales, introducing new metrics focused on reducing social vulnerability to flooding in UK government and devolved administration outcome measures could help further mitigate the social costs of flooding, which could improve upon current approaches (Sayers et al., 2017b). • It would be beneficial to understand how new developments built in at-risk areas are being made safe and resilient, for all new properties in high risk locations. This information should be publicly available by development, and should include whether properties are being protected by flood defences (and if so to what level) as well as the extent to which PFR has been implemented in new development. • The lack of a statutory requirement for SuDS across the UK, other than Wales, and lack of monitoring in all jurisdictions remains a continued challenge. With surface water flood risk projected to increase under all scenarios and the need to achieve biodiversity (and soon environmental) net gain in all new developments, there is a strong argument for greater enforcement. • Data collected for England shows that the uptake of PFR measures remains much lower than the potential cost-beneficial rate of uptake (CCC, 2019b), and there is a lack of data on uptake in the devolved administrations. Understanding of the barriers to PFR uptake has improved, informed by research in England and Scotland; subsequent recommendations now need to be acted upon. | F11: The three portfolios in the research report on future flood projections influence the future increase in risk to properties and associated EAD (Sayers et al., 2020a). In a scenario of 4°C global warming in 2100 with high population growth, continuing Current Levels of Adaptation is expected to offset future EAD in the 2080s by around £7.4 billion (all damages, not just residential, direct and indirect). Under the same scenario, an Enhanced Whole System is estimated to offset £8.2 billion EAD but only £6.4 billion is offset by the Reduced Whole System, meaning that the net increase in risk is much greater at around £2.8 billion. It is important to note that residual risk remains under all scenarios as it is not realistic to eliminate all flood risk. As detailed earlier, national strategies in place (or in train) aspire to many of the elements of the Enhanced Whole System, the degree to which these are effectively implemented will determine the level of flood risk reduction. There is a very large literature on the costs and benefits of flood protection for adaptation, indeed, it is the most comprehensively covered area in the literature (OECD, 2019). These studies tend to find high benefit to cost ratios, for both hard and soft protection measures, and for grey and green infrastructure. However, values are highly site- and context-specific. In terms of property resilience and resistance measures, there have been several studies that have investigated the costs and benefits of these measures. These include Defra (2008), EA (2015a) and Royal Haskoning DHV (2012; 2019). The most recent report from the CCC (Wood Plc, 2019) found that a number of flood resilience and resistance measures could be considered no-regret adaptation measures (i.e. a benefit to cost ratio of greater than one in cases where there is a greater than 1% chance of Annual Exceedance Probability (AEP)). In general, this literature reports that all measures are more expensive if retrofitted rather than installed in new builds. For resistance measures, the difference between costs of retrofitting vs. incorporating into new builds are more modest. However, the applicability of each of these measures depends on the type of flooding (recurrence and depth), as this alters the relative cost-effectiveness (and benefit to cost ratio). Given the residual damage costs even with current flood management policy, this is clearly an area where there are benefits of future action, and in many cases these benefits will outweigh the costs. | G11: England | H11: High | I11: High | J11: High | K11: High | L11: High | M11: Partially | N11: More action needed | O11: More action needed | P11: Medium (5) | Q11: Medium (Amber) | R11: Medium (implementation of flood policies) | Z11: Y | AA11: Y | AB11: Y | AC11: Y
A12: H04 | B12: H4 Risks to people, communities and buildings from sea level rise | C12: No | D12: 5 | E12: Our view is that there will be benefits from a ‘national conversation’ about risk acceptability, and local discussions, particularly in England and Wales, to identify the communities at risk and then develop plans for these communities including providing clear messages about how a process of change will be delivered. This brings in requirements in relation to the following areas, which Defra (Ballard et al., 2018) recently highlighted to improve coastal change in adaptation, but these apply equally to other parts of the UK: • Strategic planning o Interpretation of and required actions relating to Coastal-Change-Management-Areas. o How to bring adaptation planning in line with SMP delivery. o Improved strategies across SMPs and policy unit boundaries. • Legal o Perceived needs related to legal issues include guidance on and support with articulating a clear legal framework around adaptation planning, roll back and other adaptation policy implementation processes. • Funding – perceived needs related to funding include guidance on and support with: o Developing and delivering long-term investment strategies. o Full suite of financing options available. o How to best incentivise roll back. o Development of new financial products that could enable vulnerable communities to adapt cost-effectively. • Community engagement o Raising awareness of SMP and policies generally, including how to convey that there may be risks with policy non-deliverability due to longer term funding gaps. o Securing funds for dedicated and skilled community engagement individuals to reduce future risk and raise awareness. o Securing engagement and buy-in from elected councillors. o Strategic planning for supporting community infrastructure. o Strategic planning for caravan park businesses and their inhabitants. • Monitoring o Perceived needs related to monitoring include guidance on and support with monitoring coastal erosion, monitoring property and infrastructure at risk and when lost to coastal erosion (including temporary infrastructure e.g. caravans). | F12: In general terms, the literature reports that coastal adaptation is an extremely cost-effective response, significantly reducing residual damage costs down to very low levels (Hinkel et al., 2014). However, in locations with very few properties, such measures often have benefit-cost ratios lower than one. This may contribute to decisions that a community’s long term viability is unsustainable, when viewed from the perspective of economic efficiency. However, many more issues are involved in such cases, such as threat to life should existing or upgraded defences be breached, and there is a need for any economic analysis to consider the wider issues, and also consider different perspectives including social justice. | G12: England | H12: Low | I12: Medium | J12: Medium | K12: High | L12: High | M12: Partially | N12: More action needed | O12: More action needed | P12: Medium (5) | Q12: Medium (Amber) | R12: Medium (New or reviewed coastal policies and implementation of renewed flood policies) | Z12: Y | AC12: Y
A13: H05 | B13: H5 Risks to building fabric | C13: No | D13: 5 | E13: Improving housing quality has multiple benefits. There are direct benefits to health and wellbeing in addition to reducing household costs. The health burden from damp homes in particular is high. Subsidence tends to be a slowly progressing threat, and most adaptation is reactive, in the form of repair once major problems emerge. There is well established information on the costs of reactive adaptation from subsidence insurance claims (see above), and indeed insurance is an adaptation response to current and future risks. There are potential benefits from more proactive approaches, with most of the literature focusing on monitoring, measurement and prediction (e.g. Erkens and Stouthamer (2020)), and these are a low-regret option in national adaptation planning and awareness raising to households. There is a wider literature on the costs and benefits of direct intervention measures to reduce subsidence, but most of this is focused on human induced subsidence (e.g. water related). For the shrink swell subsidence of most relevance to the UK, the main options are centred on proactive approaches already in use, e.g. vegetation control (trees) and local water management. For high risk areas, these are likely to be low regret. An important response to windstorm risks is household insurance, which acts as a risk spreading mechanism for extreme wind events. The evidence from tropical wind storms indicates that retrofitting (for increased storm intensity or frequency from climate change) has high adaptation costs, especially for roofing upgrades (RMS, 2009), although it can lead to high benefits. There is less evidence for Europe, but this tends to report similar findings (Hunt and Anneboina, 2011; UBA, 2012). These sources indicate reasonable benefit: cost ratios (at least for some options) (BEIS, 2019b; Spinoni et al., 2020). For household options, costs are lower in new builds, and can include siting and orientation, design and materials. The potential for increased building codes to cope with more intense windstorms is considered a low-regret option, however a review (ECONADAPT, 2017) has identified that benefit to cost ratios vary significantly with the risk level, the marginal costs of higher resilience, the existing cost and life-time of the asset, the costs of retrofitting based on local costs of materials and labour, and on the discount rate. For damp or excessive moisture due to flooding, and intense or driving rain, the main current approach for managing risks for new buildings is through building standards and there has been recent research for moisture in buildings (MHCLG, 2019d). As highlighted above, there are potential benefits of a more integrated approach on moisture in buildings as part of a whole-house approach and accounting for the changing climate and potentially greater risks over time, although there would need to be an analysis of the potential costs and benefits of the climate uplifts, taking into account the long life-times and potential lock-in for new builds, but also the cost premium and nature of benefits (future, uncertain) (May and Sanders, 2017). The benefits of further adaptation for the existing building stock is highly variable and less well characterised, and there appears to be less economic evidence on potential options: this is identified as a potential gap. Appropriate guidance and tools to support decision-making appear to be lacking, and are needed for the implementation of adaptation measures in the next decade in order to avoid lock-in with inappropriate housing designs. | F13: N/A | G13: England | H13: Medium | I13: Medium | J13: Medium | K13: High | L13: High | M13: Partially | N13: Further investigation | O13: Further Investigation | P13: N/A | Q13: Medium (Amber) | R13: Medium (reviews of building regulations) | AA13: Y
A14: H06 | B14: H6 Risks and opportunities from summer and winter household energy demand (a) Opportunity - winter | C14: Yes | D14: 5 | E14: 5.7.3.1 Heating demand (H6) A more considered analysis of this opportunity could allow potential benefits to be maximised. This is particularly important in the context of Net Zero, where changing future heating demand could have a material impact on the potential Net Zero options. This applies equally to all UK nations, as the reduction in winter heating demand is high in all areas. There is a need for better integration of this issue in Net Zero policy analysis, and subsequent government intervention to deliver Net Zero (i.e. reduced winter heating should be considered in the package of policies, incentives and instruments that government introduces to help deliver Net Zero). There is a strong economic case for such action based on the value of information, as this could significantly reduce the costs of delivering net zero for the household sector (or put another way, in a case where this information is not included, incentives will be introduced to deliver higher heating demand than is needed). It is also highlighted that information to help households and business/industry recognise these beneficial effects, i.e. awareness raising, could help deliver the full potential economic benefits, i.e. to minimise rebound effects. 5.7.3.2 Cooling demand (H6) Additional action could be undertaken to build increased cooling demand into energy policy, including through the three areas for households identified above: • Incorporate future changes in energy demand from warmer winter and hotter summers into energy efficiency and low carbon heating policy and technologies being rolled out across the UK. • Incentivise the uptake of passive cooling over mechanical cooling measures as far as is appropriate. • Provide support for households that might experience ‘summer fuel poverty’ through e.g. inability to afford air conditioning if this is required. Mechanical cooling has costs and benefits that can be compared to alternatives. These include a wide range of options associated with buildings (passive ventiliation), behaviour, green infrastructure and land-use planning. These were set out in Risk H1. There is some information on the economics of AC versus alternatives, with analysis of the costs and benefits of many options (Grant et al., 2011; Frontier Economics et al., 2013; Adaptation Sub-Commitee, 2014; CCC, 2019d; Wood Plc, 2019). These studies generally favour passive cooling, but there are differences between existing building and new builds, and the timing of installation and when overheating risks occur in the future is also important (reflecting the different cost profile of capital and operating costs). At the current time, the higher externalities of air conditioning (carbon and air pollution) tend to reduce the attractiveness of this option, but this will change with decarbonisation of the electricity system under Net Zero. In a case where air conditioning is not discouraged (i.e. if choice of cooling is left to households and the private sector, and therefore met with mechanical cooling, passive or other alternatives, or cooling demand is unmet), then it would be expected that penetration rates for AC would rise significantly in England (as indicated in the evidence above). In this case, there would still be benefits from further action, notable with energy efficiency standards for cooling equipment (Low or no-regret), as well as energy efficiency awareness programmes (as there is currently for heating). Such programmes already exist for commercial buildings, but have not yet been transferred to residential ones. In a case where passive cooing is favoured, there are a range of further actions needed, which are set out in H1. | F14: N/A | G14: England | H14: Medium | I14: High | J14: High | K14: High | L14: High | M14: No | N14: More action needed | O14: More action needed | P14: N/A | Q14: N/A | R14: High (Net Zero) | W14: Y | AA14: Y
A15: H07 | B15: H7 Risks to health and wellbeing from changes in air quality | C15: No | D15: 5 | E15: The main actions that will have benefits in the next five years are further implementation of the Clean Air Strategy and uptake of the recommendations by the Chief Medical Officer. Any actions that reduce emissions of outdoor pollutants (and pollutant pre-cursors) will generally also have a positive effect on future air quality. Further research is required on the implications of climate change for wildfire and pollen risks. Further research is needed on the interactions between air pollutants and heat exposures. For indoor air pollution, NICE recommends the following actions to regulators to improve indoor air quality, which will also have benefits for future episodes of poor indoor air quality driven by hot weather, or increased levels of damp or mould (NICE, 2020): • Update existing ventilation standards, for example building regulations, or develop new ones for indoor air quality. Base them on current safe limits set for pollutants in residential developments. See, for example, World Health Organization guidelines on selected pollutants (WHO, 2010) and dampness and mould (WHO, 2009b), and the Public Health England indoor air quality guidelines for selected VOCs (PHE, 2019a). • Use existing building regulation enforcement activities to improve indoor air quality. Ensure enforcement takes place within the specified timelines. See the government's Building Regulations 2010 (UK Government, 2010) and Housing health and safety rating system operating guidance, and the Planning Portal's Failure to comply with the building regulations. It is important to consider the health co-benefits and possible trade-offs of potential adaptation actions to address the climate-driven aspects of air quality. Nature-based solutions including tree planting have been proposed to improve air quality under climate change (Seddon et al., 2020). The effect of tree planting on air quality is dependent on the scenario, scale and species used, and it is unlikely to be a major intervention to improve air quality (AQEG, 2020). Air quality gains from nature-based solutions can be marginal and other actions are also needed. Additional benefits to health and wellbeing can be drawn from increased use of green spaces (Wuyts et al., 2008; Osborne et al., 2017; Fleming et al., 2018). Promoting the planting of trees, especially in urban areas along roads has complex effects. Vegetation can simultaneously act as a very local physical barrier (and pollutant depositional sink) between source and receptor, and as an impediment to pollutant dispersal. The net effect will be highly dependent on specific local factors, and it is not possible to generalise other than to say that it is a local effect. Tree planting may also have adverse effects for the concentration of pollen and increase allergic responses (Fleming et al., 2018; Scottish Government, 2020b). | F15: There has been detailed analysis of the costs and benefits of options for reducing outdoor air pollution, which have supported the development of national air quality standards and policies from the European Commission’s Clean Air For Europe package and policies (EC, 2013) and the UK Clean Air Strategy (Defra, 2019b) with well-established methods for valuation (Defra, 2020a). It is also highlighted that these existing air quality policies will significantly reduce air pollution levels, including background levels of regional pollution from Europe (which are important for particulate and ozone levels in the UK), as well as direct emissions from sources in the UK. This means future air pollution levels should be much lower than current, and the marginal effect of climate change will act on a much lower baseline (Lacressonnière et al., 2017). The future levels of air pollution will fall even further with the implementation of Net Zero policies. There may be benefits of additional adaptation (to target climate-induced changes in air quality and with regards to Net Zero drivers) which could address the most climate-sensitive pollutants. Climate change could be more explicitly considered within existing air quality policies and identified air quality improvement measures). Potential areas where further action might be beneficial are improved early warning and response plans for extreme events, notably where there is an interaction between heat and air quality, and work on the costs and benefits of adaptation to improve indoor air quality. | G15: England | H15: High | I15: Medium | J15: Medium | K15: Medium | L15: Medium | M15: Partially | N15: Further investigation | O15: Further Investigation | P15: Low (3) | Q15: Medium (Amber) | R15: Low (no key policies in the next two years) | AB15: Y
A16: H08 | B16: H8 Risks to health from vector-borne diseases | C16: No | D16: 5 | E16: Disease and vector surveillance is a public good. There would be direct benefits to improve disease and vector surveillance in all four countries, given the very large benefits of catching vectors and pathogens before they become established. There are benefits of further action, with many low regret options to improve or modify monitoring and surveillance systems. There are some estimates of impacts and studies of willingness to pay for vaccination against tick-borne encephalitis (Slunge, 2015). Further work on vector competence would also be beneficial. Further work on modelling risk if emergent vector borne disease due to climate change through laboratory and climate driven modelling studies is also needed. The main benefits of further action are in enhanced monitoring and surveillance systems, including early warning, and these can be considered a low-regret option (WHO, 2013). Surveillance programs are highly cost effective. There are also studies that show that vaccination for tick-borne encephalitis (TBE) may be cost-effective, for people who may be exposed through work, rather than the whole population (Desjeux et al., 2005; Slunge, 2015). | F16: N/A | G16: England | H16: Medium | I16: Medium | J16: Medium | K16: High | L16: High | M16: Partially | N16: More action needed | O16: More action needed | P16: Low (2) | Q16: Medium (Amber) | R16: Medium (reviews of disease planning may emerge post-Covid, but uncertain) | AB16: Y
A17: H09 | B17: H9 Risks to food safety and food security | C17: No | D17: 5 | E17: Activities such as horizon scanning and continuous monitoring are necessary to ensure current regulations are adequate as the future to the food system is increasingly uncertain from possible emerging diseases due to climate change. Routine monitoring of food security across the UK is also essential to protect public health and limit unnecessary costs for the health and social care system. Predicting future climate risks to the UK food system will ensure vulnerable groups to food insecurity are protected and the impacts to public health are minimised. As mycotoxins may be an increasing risk the UK food system in the future, some proposed strategies in agriculture and food transport can limit the risk of fungal infections (e.g. optimal harvest timing). Additionally, adopting new farming techniques such as deep ploughing to control ergot (proposed in the Scottish Quality Crops Farm Assurance Guidance), targeting fungicide application, planting crop resistance varieties and introducing bio-control or genetic modification measures may limit the introduction of fungal spores to crops and the subsequent food system, though there are trade-offs with some of these measures, including deep ploughing (which can increase soil erosion and carbon losses) and increased used of pesticides (Food Standards Scotland, 2015). | F17: The economic impacts of food-borne disease and food safety are well understood. The FSA has developed a cost of illness model, monetising direct and indirect costs associated with food-borne illness (including food-borne Norovirus, Salmonella and Campylobacter). Measures to improve food safety, food regulations and education on food handling and safety, coupled with horizon scanning and continuous monitoring for emerging risks, are likely to be a low regret option (WHO, 2013). There are some economic studies that have assessed the economic benefits of maintaining or reducing food related disease cases in the UK under future climate change (e.g. Kovats et al. (2011)), and these find the economic benefits could be significant if the current levels of infection are maintained or increased. For food security, there are existing actions being taken to build the resilience of food supply chains, though these have a focus on the private sector. However, the complexity of supply chains and their multi-staged processes, coupled with the uncertainty around climate change impacts, indicates that the private sector might struggle to take all appropriate actions, and there is a role for Government to play in removing some of the barriers to enable and encourage private sector adaptation, as well as ensuring a higher level of resilience along supply chains. There has been some analysis of adaptation options in this area (Watkiss et al., 2019b) which has identified early low and no-regret options, but also highlighted the need for adaptive management, research and learning. | G17: UK | H17: High | I17: High | J17: High | K17: High | L17: High | M17: Partially | N17: Further investigation | O17: Further Investigation | P17: N/A | Q17: N/A | R17: Medium (new food security strategies) | U17: Y
A18: H10 | B18: H10 Risks to health from water quality and household water supply (a) water quality (b) water quantity | C18: No | D18: 5 | E18: There are likely to be benefits of further actions to improve water quality by reducing the risk of surface water flooding, such as the development of SuDS (sustainable drainage systems), catchment management, wetland creation (theses are discussed in more detail in Chapter 3 on natural environments), and improvements to bathing water quality. Nature-based solutions also help combat urban heat islands and prevent surface water and river flooding (see Chapter 3: Berry and Brown, 2021). There is some concern about chemical incidents during flooding and a need for further emergency planning (Chapter 4: Jaroszweski, Wood and Chapman, 2021). Further activities are also needed to assess the future risks to, and measures that are needed to protect, private water supplies. | F18: There are studies which have considered the overall costs and benefits of national level action to reduce the risk of water scarcity. These include supply side measures, which are discussed in Chapter 4 (Jaroszweski, Wood and Chapman, 2021). They also include marginal abatement cost curves of emergency measures for droughts (Atkins, 2018b), as well as the estimates of costs and benefits of measures to provide household water supply during droughts (National Infrastructure Commission, 2018). Alongside this, there is a complementary set of demand-side measures that can be introduced by homes, many of which are no-regret and low-regret. Water UK (2016) assessed a twin track approach of demand management coupled with appropriate development of new resources and potential transfers as being the most suitable strategy for providing drought resilience in the future. They estimated that total costs per annum for all potential future scenarios (under the Business As Usual base demand management strategy) to maintain resilience at existing levels in England and Wales are between £50 million and £500 million per annum in demand management and new water resource options. If resilience to ‘severe drought’ is adopted, this increases to between £60 million and £600 million and for resilience to extreme drought, between £80 million and £800 million per annum. There are several studies that have looked at demand side measures for households that identify a large number of low and no-regret options. The study by Arup (2008) looked at a range of water saving measures, and estimated costs and pay-back times. A similar study was commissioned by the CCC (Grant et al., 2011) looking at cost-effectiveness of alternative household options, and this was updated by Wood Plc (2019) updating a previous cost-curve study. These studies identify estimated measures with benefit to cost ratios above 1 for different house types, comparing new build vs. discretionary retrofit. The study provides unit-cost estimates for different measures, and calculated cost-curves to show their relative cost-efficiency. When considering wider benefits from a societal perspective (including avoided GHG emissions), additional no-regret measures are identified. Generally, end-of life upgrades and measures installed in new builds were more cost-effective compared to retrofits. These studies highlight the high economic benefits of further action. | G18: England | H18: Medium | I18: High | J18: High | K18: High | L18: High | M18: Partially | N18: Further investigation | O18: Further Investigation | P18: N/A | Q18: N/A | R18: Low (no key policies in the next two years) | V18: Y
A19: H11 | B19: H11 Risks to cultural heritage | C19: No | D19: 5 | E19: Further action would be beneficial with regards to mapping climate related hazards that are relevant to heritage, in understanding the vulnerability of different heritage assets to these hazards and identifying those types of assets and locations that are most at risk. The complexity of ownership of heritage assets and the synergies with landscape, land management and the natural environment mean that this is complex. Standardising data collation and facilitating sharing would help further understanding of risks and opportunities. It is very challenging to estimate the costs and benefits of adaptation for cultural heritage because of its heterogeneity. Costs are very site specific, and benefit analyses involve challenging valuation aspects that include direct and wider economic benefits, but also non-use values, the latter including option, existence, and bequest value. Further, in many cases, adaptation will be part of broader interventions targeting at risk areas, e.g. coastal or river flood management. For particularly sensitive sites, there are options for monitoring and surveillance in order to recommend both preventative and remedial action. There are also some limited examples in the international literature with case studies (ex ante and ex post), as well as willingness to pay studies that provide some estimates to compare against potential costs (for specific cultural heritage sites). For example, Pollard-Belsheim et al. (2014) investigated the effectiveness of adaptation strategies to preserve coastal archaeological sites. There are also some additional issues with the impact of climate change on artefacts inside museums and galleries. There is some evidence on the options for guaranteeing the appropriate indoor climate, which involve similar issues on the choice between mechanical or passive cooling. Coelho et al. (2020) examined such examples and report passive retrofit measures are cost-effective, but again, adaptation effectiveness will be extremely site specific. Once this is in place, then further action is required across the UK to enhance the resilience of built and natural heritage. Societies benefit from and are dependent on cultural heritage, which includes ecosystem services (e.g. marine-based livelihoods and food security) and other cultural services (i.e. non-material benefits from ecosystems). However, understanding and attributing the impacts are complicated due to the complexities of assessing, measuring and quantifying cultural services and other social benefits related to cultural heritage. More work needs to be done on the risks and benefits of adaptation options and adaptive capacity, as well as other barriers such as institutional inertia and socio-cultural acceptability of risks. | F19: N/A | G19: England | H19: Medium | I19: Medium | J19: High | K19: High | L19: High | M19: Partially | N19: More action needed | O19: More action needed | P19: N/A | Q19: N/A | R19: Low (no key policies in the next two years) | AC19: Y
A20: H12 | B20: H12 Risks to health and social care delivery | C20: No | D20: 5 | E20: This risk needs to be managed strategically at a national level. Regional/local level climate risk assessments should be carried out by Trusts, Health Boards and local government social services (where these are not already happening) to help them plan forward with climate risks in mind. As highlighted in the sections above, a particular issue is around heat risks in care settings, and thus there are similar issues for passive versus mechanical cooling options as for all buildings (see H1). There are obvious potential benefits from ensuring new care homes and hospitals are designed for the future climate. This is particularly important given the high risks and potential for lock-in involved, i.e. the higher costs of retrofitting later. There are also potential options for retrofitting existing care homes and hospitals. For hospitals, there is some literature on hospital design (including retrofitting) that emphasises passive approaches (Giridharan et al., 2013; Fifield et al., 2018) which highlight the potential benefits of such designs, but also highlights that other drivers, notably economics, are preventing uptake. However, the costs and benefits of actions, especially for retrofitting existing buildings, will be very site specific. There is some analysis of potential adaptation options for care homes (Oikonomou et al., 2020) (Gupta et al., 2016a; PHE, 2018b). These studies identify a range of options, including in care home operation (monitoring, early warning, emergency response), passive and mechanical cooling, and enhanced regulations, standards and guidance from care sector bodies and Government departments. Some initial work has been undertaken to explore a cost-benefit evaluation of building adaptations designed to protect against heat risks to residents of care homes in England (Ibbetson, 2021). The work found that various physical adaptations have the potential to at least be cost-effective and reduce heat risk. For example, in one case study, external window shading was estimated to reduce mean indoor temperatures by 0.9°C in a ‘warm’ summer and 0.6°C in an ‘average’ summer. In this case, for a care home of 50 residents, over a 20-year time horizon and assuming an annual discount rate of 3.5%, the monetized benefit of reduced Years of Life Lost (YLL) would be between £44,000 and £230,000 depending on which life-expectancy assumption is used. Although this range represents appreciable uncertainty, it appears that modest cost adaptations to heat risk may be justified in conventional cost-benefit terms even under conservative assumptions about life expectancy and should therefore be considered as an important complement to operation responses. Other adaptation options can be considered low regret (i.e. heat management plans, some passive ventilation measures). Further investigation of the range of adaptation options across the UK would be highly beneficial. Given these gaps in understanding, further action is therefore needed to specifically address the risk of overheating in residential care buildings. Adaptations through design measures (such as glazing improvement (where needed), draught proofing, shutters, reflective surfaces, green cover and green space, and ceiling fans) can help to reduce the risk of overheating in the next five years (see also discussion of housing interventions above). Monitoring of indoor temperatures and other indicators would be an additional response. Indoor temperature/ thermal comfort monitoring could be installed in a stepwise method, to monitor changes over time. The COVID-19 pandemic may have long term implications for the resilience of the health and social care sector. The pandemic has caused additional stress on the health and social care system due to increased demand (likely to last until 2022) and additional pressures on local finances (likely to last longer term). | F20: N/A | G20: England | H20: Medium | I20: Medium | J20: Medium | K20: High | L20: High | M20: Partially | N20: More action needed | O20: More action needed | P20: Medium (5) | Q20: Medium (Amber) | R20: Medium (reviews of health and social care planning may emerge post-Covid, but uncertain) | AA20: Y | AB20: Y
A21: H13 | B21: H13 Risks to education and prison services | C21: No | D21: 5 | E21: 5.14.3.1 Education (H13) Across the education system, many schools are limited in their resources, are older buildings, and staff lack sufficient knowledge, hindering effective climate adaptation planning to respond to and recover from extreme events. The general set of adaptation interventions for schools are similar to other buildings, although there are additional low regret options for behavioural responses and emergency plans. There is some specific information on potential options and general affordability (e.g. GLA (2020)), as well as potential benefits (noting these include reduced cognitive and learning issues, mental health, and lost school days). Thompson et al. (2015) report on several projects under the Innovate UK’s Design for Future Climate, Adapting Buildings (D4FC) programme, which included schools, with reported costs for adaptation measures. There is also some international literature which identifies the benefit to cost ratios for greening schools (Kats, 2003, 2006; Zhang et al., 2018) which report higher costs, but net benefits when considered on a life cycle basis. However, costs and benefits vary on a case-by-case basis, and between retrofits and new buildings. Further adaptation measures are essential to avoid lock-in with building designs and adapt to the future risks of overheating, flooding and other climate hazards. Importantly, the first step for adaptation is developing a school climate adaptation plan with specific targets, strategies, tasks and roles to ensure its delivery and effectiveness. This plan must be centred to ensuring child health and wellbeing, thus engagement across the whole school system, including school decision makers and external support is necessary with the aim to increase the school’s adaptive capacity. A whole school approach is desired to reach optimal effectiveness, considering positive and negative measures and how they interact, but also how this plan integrates with the wider school agenda. Having a school climate adaptation plan delivers multiple positive outcomes including reduced bills, increased learning opportunities, improved biodiversity and better air quality. A variety of adaptation measures targeted at school buildings have also been proposed by the Greater London Authority that are specific to London Schools, but are likely relevant to the UK-wide context (GLA, 2020). These include multiple modifications to roofs such as green or blue roofs and cool roofs which are reflective or light in colour. As overheating is increasingly becoming a high risk to schools, many measures suggested are around cooling technologies and ventilation. Examples of these systems include windcatchers – natural ventilation systems harnessing wind blowing to ventilate indoor areas – automated window ventilation, hybrid natural and mechanical ventilation, and mechanical cooling or air movement (air conditioning). Additional measures to manage heat risks include thermal massing and solar shading – interception of sunlight to reduce heat entering buildings. Many measures have been proposed as effective adaptive strategies for school outdoor grounds across difference space requirements and resource availabilities (GLA, 2020). For schools with limited space availability, rain planters and gardens, tree and shade structures, drain filters and permeable or green surfaces are effective ways to manage heat, flood and water scarcity risks through increasing shade, water availability, biodiversity and promoting draining of excess water. Additionally, schools with more space availability can install or adopt below- or above-ground rainwater attenuation tanks and ponds to store excess rainwater and potentially regulate local temperature, reducing the urban heat effect. Furthermore, some measures require a large area, thus schools with the available space can implement a swale – a shallow ditch to store, transport and absorb run-off – or a basin – a shallow depression in the ground covered in grasses to capture water, reducing run off. Schools should also consider ways to reduce the risk of water shortages by limiting their reliance on the mains water supply (see Risk I8 in Chapter 4: Jaroszweski, Wood and Chapman, 2021). To reduce water use, schools can install tap aerators and low flow taps which reduce flow of water through taps by up to 50%; also dual flush toilets allow two available flush volumes, reducing water consumption. Furthermore, reducing usage through behavioural changes to minimise consumption and wastage will have a positive impact on London’s water supply. Additional building modifications include increasing the permeability of surfaces to replenish the water table, which has added benefits for reducing flood risk and harvesting rainwater for non-drinking purposes (GLA, 2020). | F21: N/A | G21: England | H21: Medium | I21: Medium | J21: Medium | K21: High | L21: High | M21: Partially | N21: More action needed | O21: More action needed | P21: N/A | Q21: N/A | R21: Low (no key policies in the next two years) | AA21: Y
A22: I01 | B22: I1 Risks to infrastructure networks (water, energy, transport, ICT) from cascading failures | C22: Yes | D22: 4 | E22: 4.2.3.1 Additional adaptation that would address the adaptation shortfall (I1) There are beneficial adaptation actions which could be enacted during the next five years. However, the benefits of these actions are often primarily aimed at a particular infrastructure system, and hence also relate to other risks within this report. For instance, Thacker et al. (2018) demonstrate the benefits of bringing forward adaptation work in the protection of electricity substations. The study concentrates on the ETR 138 recommendations that major electricity assets be made resilient to a 1:1000-year flood. By simulating the potential costs involved in cascading impacts of flood-related substation failure it is found that (i) building a wall is cost beneficial for all substations; (ii) relocating the substation is not cost beneficial in most cases; and (iii) in approximately 50% of cases, raising the substation would be cost beneficial. CCC (2017) argue that common standards of resilience (such as ISO 14091) would help with investment planning and help emergency planners better understand the potential for service disruption arising from assets in their area. ETR 138 ‘Resilience to Flooding’ is given as a good example that has been adopted within the electricity transmission and distribution sector. It is stated that enhanced arrangements for information sharing on critical risks of interdependence are required to assist in creating the appropriate institutional conditions for adaptation. | F22: There is some evidence on the potential costs and benefits of adaptation for infrastructure investment (OECD, 2015) and in general positive benefit-to-cost ratios are reported for making infrastructure resilient (GCA, 2019). However, there is little evidence on the economic benefits for addressing cascading risks or moving to a systems-based approach. The studies that do exist tend to assess the additional benefits in considering indirect costs from adaptation (rather than just the avoided costs of damage to the infrastructure asset and operation itself), e.g. Thacker et al. (2018) for electricity substations, and Pant et al. (2020) for multiple networks. The consideration of indirect risks increases benefit streams and thus leads to higher economic benefits (and NPVs/BCR ratios). Evidence from other countries highlights that a systems-approach can also highlight the key vulnerability pinch points in networks, and thus help to direct adaptation, e.g. over-designing some key nodes or elements of the network. | G22: England | H22: High | I22: High | J22: High | K22: High | L22: High | M22: Partially | N22: More action needed | O22: More action needed | P22: Low (1) | Q22: Medium (Amber) | R22: High (review of national risk assessments) | V22: Y | W22: Y | X22: Y | Y22: Y
A23: I02 | B23: I2 Risks to infrastructure services from river, surface water and groundwater flooding | C23: No | D23: 4 | E23: 4.3.3.1. Additional planned adaptation that would address the adaptation shortfall (I2) As recommended in CCRA2 (Dawson et al., 2016), there remains a need for the development of consistent indicators of network resilience to flood risk across all critical national infrastructure sectors and networks. Such indicators would help to create the institutional conditions for adaptation and would allow for improvements to be measured over time. This could build on improvement in local hazard information, such as the Cabinet Office’s Resilience Direct platform which provides street-level surface water flood forecasts to authorities and category 1 and 2 responders. In response to modelled impacts on emergency services due to observed surface and fluvial flooding in York, Coles et al. 2017 argued that an appropriate adaptation strategy should identify areas on the road network that are most vulnerable to flooding, as well as parts of the road network that are crucial for emergency services, e.g. access to hospitals. Green et al. (2017) recommended that the ambulance service should ensure that they are situated at strategic stand-by points during flood conditions to minimise the impact of a blocked road network on delaying emergency response to vulnerable locations. For urban road transport, Pregnolato et al. (2016) suggest both green infrastructure and conventional engineering measures to improve resilience. Spatial distribution of green roofs reduced person delays during a 1 in 10-year flood by 26%, compared with 12% from hard engineering measures for a single junction (both are compared with the effects of a 1 in 10-year flood with no adaptation), which highlights the potential benefits of blue-green infrastructure for urban flood resilience. The economic feasibility of this measure has not been assessed. As covered in Risk I1, Thacker et al. (2018) demonstrate the benefits of bringing forward adaptation work in the protection of electricity substations. It is estimated that if National Grid brought forward the entirety of planned works scheduled for 2022, this would result in additional savings of £133,260,000 in avoided expected annual losses (although this would be constrained by planning and time scale). It must be noted that this research is based on simulation work. | F23: There is evidence on the potential costs and benefits of further adaptation. Much of this indicates high economic benefits from investing in flood adaptation for infrastructure (OECD, 2015: GCA, 2019). However, some care should be taken in interpreting this evidence, as much is based on ‘predict and optimise’ studies (where future risk levels are known), rather than an analysis taking account of uncertainty (and thus the potential for under or over investment). The effects of different adaptation strategies on the annual expected damages from river flooding in the UK can be estimated from a recent EU+UK-wide regional climate change impact assessment (Dottori et al., 2020), which used a regional-scale hydrological model with country-specific flood depth-damage functions to simulate economic damages under different global warming and adaptation scenarios. Without adaptation, annual expected damages increase from 0.03% of UK GDP nowadays, to 0.04 and 0.06% of GDP with 2°C and 3°C global warming respectively (assuming the population and economy of 2100). However, the impacts are significantly reduced with adaptation. With 3°C global warming by 2100, the reduction in expected annual damage compared with no adaptation, in 2100, is 87% for raising of dykes, 94% for retention areas, 39% for relocation of built-up areas and 50% for building damage reduction measures. More generally, there are a range of low-regret measures that have been identified in this area (Vallejo and Mullan, 2017; Watkiss et al., 2019), which include: • Supporting decision-making by providing tools and information, • Screening climate risks (climate risk management) in public investments, • Screening climate risks (climate risk management) in private sector investments, • Enabling infrastructure resilience through policy and regulation, • Encouraging the disclosure of climate risks/uptake in commercial finance, • Supporting innovative risk spreading (insurance). There are also estimates of the economic benefits and costs of some green infrastructure (McVittie et al., 2017), though these are often site-specific. It is highlighted that there are important governance challenges, as well as opportunity and transaction costs associated with green infrastructure (Watkiss et al., 2019). The benefit to cost ratios of SuDS have been studied (e.g., Ossa-Moreno et al., 2017), and guidance exists for estimation (Benefit of SuDS Tool (BeST) (UKCIRIA)), although the financial case alone does not appear to incentivise adaptation. | G23: England | H23: High | I23: High | J23: High | K23: High | L23: High | M23: Partially | N23: More action needed | O23: More action needed | P23: N/A | Q23: Medium (Amber) | R23: Medium (implementation of flood policies) | V23: Y | W23: Y | X23: Y | Y23: Y | Z23: Y
A24: I03 | B24: I3 Risks to infrastructure services from coastal flooding and erosion | C24: No | D24: 4 | E24: 4.4.3.1 Additional planned adaptation that would address the adaptation shortfall (I3) There is increased realisation that it is unrealistic to promote a ‘hold the line’ policy for much of the coastline. The CCC (2018a) highlighted that 1,460 km of coastline in England designated as 'hold the line' to the end of the century, achieves a much lower benefit-cost-ratio than the flood and coastal erosion risk management interventions that are government-funded today. On this basis therefore, funding for these locations is unlikely and realistic plans to adapt to the inevitability of change are needed now. This raises the fundamental questions of how to: (i) plan our future shoreline on the open coast and along estuaries; and (ii) deliver practical portfolios of adaptation options that are technically feasible, balance costs and benefits, can attract appropriate finance, and are socially acceptable. Recent research commissioned by the CCC (Jacobs, 2018) has explored the application of adaptation pathways to help explore alternative sequences of adaptation responses to climate change at a sample of coastal sites. The process of developing and evaluating alternative adaptation pathways allows potentially flexible responses to be explored in the face of uncertainty. As noted earlier, there are significant uncertainties inherent in estimating the rate of mean sea-level rise and the future frequency and severity of extreme coastal events that drive coastal erosion and flooding. The use of adaptation pathways for the long-term planning of flood risk management, first used in developing the Thames Estuary 2100 flood risk management strategy (Environment Agency, 2012), has been shown to be a promising technique that is being applied more widely (e.g. in developing the Humber 2100+ flood risk management strategy). The Environment Agency committed to increase use of adaptive management in flood and coastal risk management (Environment Agency, 2020a). As mentioned earlier, Hall et al. (2019) quantify sequences of adaptations that would be needed to protect London from flooding by the sea to the year 2300. The approach is transferable to other vulnerable coastal cities of high strategic, economic and political importance. Much of the work required in this area revolves around better understanding risk. Firstly, comprehensive data on the scale of risk from coastal erosion and flood risk for roads, ports and airports are required for future climates. Secondly, better monitoring and evaluation of existing policies would be beneficial to determine to what extent these are managing the risk down (such as with the risk of flooding to rail). Given the uncertainties around sea level rise, ‘what if’ planning for high coastal risk scenarios would be beneficial for understanding what could be done in the event of very high rates of change. | F24: In general terms, the literature reports that coastal adaptation is an extremely cost-effective response, significantly reducing residual damage costs down to very low levels (Hinkel et al., 2014). The National Infrastructure Commission (2018c) analysed the investment that would be required to provide a range of resilience standards for coastal flooding. The benefits of achieving a resilient infrastructure sector were estimated as the value of the ‘avoided’ or ‘mitigated’ damage and disruption caused by climate-induced events. Similar analysis was undertaken by the Environment Agency (2014), updated in Environment Agency (2019b), who estimated that the net present value of the optimised long-term investment in flood and coastal erosion risk protection, including the economic damages avoided by making the investment, including the benefits of protecting infrastructure. | G24: England | H24: Medium | I24: Medium | J24: Medium | K24: Medium | L24: Medium | M24: Partially | N24: Further investigation | O24: Further Investigation | P24: N/A | Q24: Medium (Amber) | R24: High (New or reviewed coastal policies and implementation of renewed flood policies) | V24: Y | W24: Y | X24: Y | Y24: Y | Z24: Y
A25: I04 | B25: I4 Risks to bridges and pipelines from flooding and erosion | C25: No | D25: 4 | E25: 4.5.3.1 Additional planned adaptation that would address the adaptation shortfall (I4) For pipelines, the Energy Network Association (2015) stated improving drainage in areas that regularly flood during extreme weather events is one strategy of adaptation; monitoring of river and coastal erosion, as well as the development of flood, coastal and updated contingency defence measures as further strategies. Pipeline operators may be forced to follow new land zoning codes or adaptation measures such as re-routing lines from high-risk areas, and structural upgrades to existing infrastructure. For bridges, Nasr et al (2019) found that scour depth can be reduced by streamlining abutments by means of wing walls, and piers by means of cutwaters. Alternatively, the use of stone pitching to armour the riverbed around abutments and piers is a very effective way to prevent scour. Reforming maintenance and inspection manuals should accommodate the effects of climate change, e.g. through a revision of the design codes to account for the effects of climate change, specifically in relation to bridge foundation scour and the effects of increased wetting and drying of soils in which pipelines are buried. Mitigation methods suggested include new protocols of maintenance and early-warning systems, however more data are needed to support this direction of development. Sayers et al. (2015) state that the most significant adaptation is likely to come through changes in maintenance operations, improving collaboration with emergency managers, recognising emergency management as an integral function of managing infrastructure. | F25: The costs of adapting pipelines and bridges to climate change are very site-specific, and costs vary significantly between adapting the current stock versus new infrastructure. There is some older literature on the costs of adaptation for bridges (road and rail bridges) to address scour risk (Nemry and Demirel, 2012), which includes estimates for the UK and Ireland where annual costs are estimated at €47 million/year in the 2050s. Of these costs, 80% are for road and 20% for rail bridges. This is reported at approximately 2% of current road maintenance costs. The benefits of adaptation – in terms of avoided scour, possible failure, and subsequent repair or reconstruction (and indirect effects include travel time losses) – were not assessed, though the costs of any failures are normally large. Bridges and tunnels have a long service life which makes them priority assets for adaptation. Lamb et al. (2019) considered the economic costs of bridge failures due to scour over the Great British rail network, including travel time costs, estimating the annual risk (expected annual utility cost to passengers, but excluding freight and speed restrictions when scour damage is suspected) of between £6 million and £60 million. This provides some baseline costs, onto which future climate risks will act, and adaptation could reduce. The Tomorrow's Railway and Climate Change Adaptation (TRaCCA) programme did look at options for the rail network overall to adapt in the most cost-effective way, with some quick wins suggested, although for scour this focused on better vulnerability information (RSSBa, 2016). For the road network, Atkins (2013a) looked at the potential risks of climate change on road bridges for the Highways Agency (but considered all risks, not just scour). This looked at reduced service life, additional maintenance and associated lane closures, and found the benefits of adaptation were similar to costs for central scenarios (with benefit to cost ratios close to one) but BCRs rose significantly under worst case scenarios. | G25: England | H25: Medium | I25: Medium | J25: Medium | K25: Medium | L25: Medium | M25: Partially | N25: Further investigation | O25: Further Investigation | P25: N/A | Q25: N/A | R25: Medium (implementation of flood policies) | W25: Y | X25: Y | Y25: Y
A26: I05 | B26: I5 Risks to transport networks from slope and embankment failure | C26: No | D26: 4 | E26: CCRA2 stated that further action was required to ensure that projected increases in heavy rainfall events are factored into long-term renewal programmes for earthworks, especially for the rail network. This will reduce vulnerability now and is likely to be cost-effective to implement, given that the risk is increasing with further asset deterioration combining with heavier and more frequent rainfall events. Adaptation methods suggested within the current literature focus on providing improved numerical tools for infrastructure asset owners to predict failure occurrence, improved instrumentation and monitoring systems to detect pre-failure slope behaviour linked to decision support systems, more detailed characterisation of engineered soil assets, continued use of slope inspection programs, and greater use of soft engineering techniques such as vegetation management to reinforce vulnerable slopes. Some deterioration methods are not fully understood, which will impact adaptation strategies. Hughes et al. (2016) discuss the need for continuous monitoring of pore pressures during and after construction; this is mentioned as an adaptation measure. | F26: There are some clear low-regret options for addressing these risks. For railways, inspection and maintenance are key activities to monitor slope and embankment failure risks in advance, at a relatively low cost (RSSB, 2016b). Currently, routes use a drainage decision support tool and data collected from drainage inspections, surveys and assessments, with drainage assets currently required to be inspected at least every five years (Haines, 2020). A low-regret option would be to increase inspection frequency (especially for higher risk areas). Drainage is also key for the stability and resilience of earthworks. There are obvious low-regret and easily implementable options for enhanced maintenance of drainage systems for addressing surface and groundwater water away from roads and railways. The costs of increasing drainage capacity in new road infrastructure also appears to be low regret, adding only a small percentage to the overall construction costs. For new builds, there are also options for improving monitoring around complex systems such as embankments; Tang et al. (2018) recommend remote sensing tools and report that new engineered slopes are an opportunity to design intelligent monitoring systems in a cost-efficient way, e.g. by installing systems during construction rather than retrofitting them later. There is mixed evidence about the effectiveness of specific interventions such as vegetation management. This can help manage soil moisture fluctuations in the near-surface zone (Tang et al. 2018), and there is evidence that mature trees have positive effects on embankment slopes (Smethurst et al., 2015). However, Network Rail reported that the removal of trees is not necessarily the cause of landslips; during summer they may cause the earthworks to dry out, and they can pose additional risks during windstorms. On the contrary, there is an increased incidence of trains running into fallen trees; vegetation management has a role to play in mitigating climate risk of earthworks, but it needs trade-off between benefits and risks (e.g. at the toe of an embankment). Network Rail spent approximately £100 million on earthworks and drainage investment per annum (on average) from 2009 to 2014 and was planning to double this in the subsequent five years. The benefits of these investments are in terms of avoided damage, which are very large for rail slope and embankment failure. Similar considerations are made for highways, where the costs of planned maintenance work are weighed against the risks of highway closure and repair and travel time delays. However, there is high heterogeneity with site and location (Glendinning et al, 2014) which means adaptation is context specific (and thus so are benefits and costs). | G26: England | H26: Medium | I26: Medium | J26: Medium | K26: Medium | L26: Medium | M26: Partially | N26: More action needed | O26: More action needed | P26: Medium (5) | Q26: High (Green) | R26: High (Network Rail review of vulnerability of the rail network following the Stonehaven crash) | Y26: Y
A27: I06 | B27: I6 Risks to hydroelectric generation from low or high river flows | C27: No | D27: 4 | E27: 4.7.3.1. Additional planned adaptation that would address the adaptation shortfall (I6) For new schemes, ensuring climate impacts are considered in both site selection and design will enable owners to maximise the system outputs under future climate and minimise risks of damage as far as it is possible to protect from high end events. As highlighted above, guidance is available to help such assessments (IHA, 2019). For existing schemes, retrospective climate risk assessments can better inform operational planning and take action, if necessary, to protect assets and the downstream environment from harm during high water flows or flooding. For both run-of-river and impoundment schemes, UKCP18 consistent projections of river flow and catchment processes would be required to assess the implications of future flow patterns on their operation and revenues, and in particular to assess the risks of damage to hydro-electric power infrastructure from extreme high flow events, together with the implications of changing temperatures and the patterns of drought and rainfall on embankment safety. For existing reservoir or impoundment-based hydroelectric schemes, the suitability of spillways to future peak flow should be ensured, updating probable maximum flow rates to include climate change (Duncan et al. 2010). For existing and future run-of-river schemes assessing their suitability under future low and peak flows is necessary, adaptations could involve incorporating a weir – however there are wider ecological implications of weirs, making this option unsuitable (Duncan et al. 2010). To increase hydro power output from existing run-of river schemes during periods of increased winter flow, larger turbines can be installed (Sample et al. 2015), although Sample notes that increasing turbine size to take advantage of increased flows during winter would likely be at the expense of reducing further output during periods of low flow. For impoundment schemes to take advantage of higher winter rainfall, increases in reservoir sizes and or turbine capacity will be necessary (Duncan et al. 2010; Sample et al. 2015). | F27: There is now considerable information on the technical adaptation options available for the hydro-electric generation sector, including sector specific guidance (IHA, 2019), albeit primarily focused on new builds. There are also many international studies that look at the costs and benefits of adaptation, for current plants and especially new build (e.g. Nassopoulos et al. 2012; Cervigni et al., 2015; NRDI, 2016). There are also several studies that look at the potential economic costs of changes in rainfall and river flows, and thus hydroelectric generation at the European level, which include analysis of the UK (van Vliet et al. 2016; Tobin et al., 2017; Després and Adamovic, 2020). These studies project increases in hydro generation output with climate change, but there are large differences between studies (and projections and scenarios) including some projections of reductions in output, and differences between storage and run-of-river. Consideration of different studies reveals the considerable uncertainty involved, and thus the need for both low and no-regret options and iterative adaptive management. For new plants (although these are not a major focus for the UK, even under net zero scenarios), decision making under uncertainty is key, and has been applied (see international studies above). For existing plants there are a set of no-regret options for high flows, notably with weather and climate services, for both extreme events and early warning but also more general reservoir operation optimisation. There are also various engineering options for additional spillways, and measures such as fuse gates which can be added, which are generally considered low-regret options for addressing high flow risks. There are more structural options to address changes in flood return period and peak intensity, but these tend to be much more expensive. The large downside risks for hydropower revenues are from low flows during periods of drought, especially for run-of-the-river plants. Most adaptation studies focus on turbine upgrades (e.g. EBRD, 2015) which are more cost-effective than larger structural changes (dam heightening, conveyance structures), although there is usually some degree of trade-off (i.e. lower optimisation but greater flexibility for flow variation). Turbine upgrades also offer some potential to take account of upside risks. There is greater potential for including all these adaptation measures in the design and construction of new projects, and decision scaling has been quite widely applied to take account of climate risks and plan adaptation at the international level for such assessments (e.g. Ray et al., 2015; Karki et al. 2015), and is incorporated in the IHA guidance (2019). However, there is often a careful balance of costs and benefits of adaptation, because of the upfront costs, versus the benefits in terms of future (and thus discounted) benefit streams. | G27: England | H27: Low | I27: Medium | J27: Medium | K27: Medium | L27: Medium | M27: Partially | N27: Further investigation | O27: Further Investigation | P27: N/A | Q27: N/A | R27: Medium (reviews underway of environmental permitting) | W27: Y
A28: I07 | B28: I7 Risks to subterranean and surface infrastructure from subsidence | C28: No | D28: 4 | E28: 4.8.3.1 Additional planned adaptation that would address the adaptation shortfall (I7) More research is needed for the production of more accurate and consistent data, for investigating the interdependencies of infrastructure and understanding potential adaptation strategies (mainly limited to monitoring at present). The heterogeneity of railway earthworks is a challenge to understanding their future behaviour. More detailed information on sub-surface composition would assist in predicting future behaviour but would be costly to achieve. Quantifying the uncertainty in soil properties would be beneficial. Removal of trees from railway embankments has been shown to reduce shrink-swell movement, though this comes at a cost of reducing the reinforcement effect of tree roots and increases in pore water pressure leading to loss of stability (Briggs et al., 2016). Increased ground and weather monitoring and the use of real-time decision support tools has been proposed as a potential method to mitigate the risks of shrink-swell. | F28: Land subsidence tends to be a slowly progressing threat, which can reduce the incentives for early action (Erkens and Stouthamer, 2020). As a result, most information is on repair costs, i.e. after subsidence has occurred (especially for residential and commercial properties). As highlighted above, there are some potential risks for rail tracks (but lower risks for highway pavements) as well as potentially some risks to buried infrastructure. There are some low-regret options, e.g. increased monitoring in higher risk areas, as well as vegetation control, but there appears to be little information on the costs and benefits for future climate risks. | G28: England | H28: Low | I28: Medium | J28: Medium | K28: Medium | L28: Medium | M28: Partially | N28: Further investigation | O28: Further Investigation | P28: N/A | Q28: N/A | R28: Low (no key policies in the next two years) | V28: Y | W28: Y | X28: Y | Y28: Y
A29: I08 | B29: I8 Risks to public water supplies from reduced water availability | C29: No | D29: 4 | E29: 4.9.3.1 Additional planned adaptation that would address the adaptation shortfall (I8) The CCRA3 water resources project (HR Wallingford, 2020) finds that the only scenarios that result in a significant UK-wide supply-demand balance surplus are ones in which additional adaptation action is taken to reduce demand or where the current and announced adaptation scenario is applied to the central population. This scenario includes the water companies’ own ambitions for reducing per capita consumption for England and Wales, baseline values were used for Scottish Water and Northern Ireland water as those companies have reported no intention to significantly increase meter penetration in households or other measures to reduce household consumption. Considering reservoirs, the routine use of climate projections and their potential impacts on the bund and spillways during safety inspections and mid- to long-term planning would better protect them from failures exacerbated by climate change. Establishing appropriate leakage targets using a sufficiently wide assessment framework considering all potential users may improve multi-sector resilience and economic efficiency of water and water rights use. Defra announced it is looking to bring in a statutory long-term water demand target by October 2022. The target will likely combine demand on public water supplies from households, business and due to leakage. | F29: There are estimates in the literature on the benefits of further action. In terms of the supply side there are several studies that have considered additional measures, but these focus more on drought. Water UK (2016) estimated that a ‘twin track’ approach of demand management coupled with development of new resources and potential transfers is the most suitable strategy for providing drought resilience in the future. They estimated that total costs per annum for all potential future scenarios (under the business as usual base demand management strategy) to maintain resilience at existing levels in England and Wales are between £50 million and £500 million per annum in demand management and new water resource options. If resilience to ‘severe drought’ is adopted, this increases to between £60 million and £600 million and for resilience to extreme drought, between £80 million and £800 million per annum. The National Infrastructure Commission (2018b) estimated that in England alone the total costs between 2020 and 2050 of implementing emergency measures to provide household water supply during a 0.5% drought, weighted by the occurrence probability, range between £13 and £16 billion. The total costs over the same period of implementing emergency measures against a 0.2% drought range between £21 billion and £27 billion (costs on a present value basis (2018 prices) weighted by the occurrence probability). Atkins (2018) used cost benefit analysis to build marginal abatement cost curves of emergency measures, i.e. when drought severity is beyond the capacity planned for through long-term water resources planning. This included examples for the Thames Basin. The results indicate that many emergency measures would be challenging to implement, provide uncertain yields and incur significant costs (Atkins, 2018). There is also a suite of demand side measures that can be introduced by homes, many of which are no-regret and low-regret. Water UK (2016) assessed a twin track approach of demand management coupled with appropriate development of new resources and potential transfers as being the most suitable strategy for providing drought resilience in the future. They estimated that total costs per annum for all potential future scenarios (under the business and usual base demand management strategy) to maintain resilience at existing levels in England and Wales are between £50 million and £500 million per annum in demand management and new water resource options. If resilience to ‘severe drought’ is adopted, this increases to between £60 million and £600 million and for resilience to extreme drought, between £80 million and £800 million per annum. There are several studies that have looked at demand side measures for households that identify a large number of low- and no-regret options. The study by ARUP (2008) looked at a range of water saving measures, and estimated costs and pay-back times. A similar study was commissioned by the CCC (Davis Langdon, 2011) looking at cost-effectiveness of alternative household options, and this was updated by Wood Plc (2019), updating a previous cost-curve study. These studies identify estimated measures with benefit to cost ratios above 1 for different house types, comparing new-built vs discretionary retrofit. The study provides unit-cost estimates for different measures, and calculated cost-curves to show their relative cost-efficiency. When considering wider benefits from a societal perspective (including avoided GHG emissions), additional no-regret measures are identified. Generally, end-of life upgrades and measures installed in new builds were more cost-effective compared to retrofits. These studies highlight the high economic benefits of further action. Research by Artesia (2019) for Water UK assessed the savings, costs and benefits of 18 water demand reduction interventions. It was estimated that with concerted effort by government departments, regulators and water companies, £64 benefit for every £1 spent could be achieved. The report found that the best strategy to maximise demand reductions involved mandatory water labelling and increased smart metering (above that in current water company plans). It was estimated that a 2,300 Ml/d reduction in demand beyond current ambitions could be achieved through these measures. Additional information on research regarding the costs and benefits of additional measures is set out in Table 4.32 below. | G29: England | H29: Medium | I29: High | J29: High | K29: High | L29: High | M29: Partially | N29: More action needed | O29: More action needed | P29: High (8) | Q29: High (Green) | R29: Medium (upcoming plans for water efficiency and reducing demand, next round in water resources planning in a few years' time) | V29: Y
A30: I09 | B30: I9 Risks to energy generation from reduced water availability | C30: Yes | D30: 4 | E30: 4.10.3.1 Additional planned adaptation that would address the adaptation shortfall (I9) With respect to guiding new small plants which fall under the major infrastructure project thresholds and those already built on inland sites, further actions are warranted given abstraction reforms remain to be implemented in England and Wales, which, together with climate projections for the future water resources available in different catchment areas (Sayers et al., 2020), could guide new infrastructure siting and cooling technology choices. The evidence for risks to energy generation due to higher water temperatures and/or reduced river flows should be kept under review, with long-term monitoring of risk levels and adaptation activity as advised in CCRA2, with additional consideration of how an expansion in hydrogen and biofuel production in the UK would affect vulnerability to reduced water availability. | F30: The costs of further monitoring, and some strategic analysis to look at water related risks (water demand and flooding) for Net Zero generation, are low-regret options and would have clear benefits through the information provided. For existing thermal plants, there are low regret adaptation options centred on monitoring of risk levels, including early warning and subsequent emergency management during extremes. In other European countries, where these risks have already materialised, adaptation options have focused on demand management and there is some analysis (Perrels et al., 2015) of the economic benefits of demand management options (for industry) and the potential use of smart grids to help manage non-essential energy use during these events; these might provide options should risks increase in the UK. There are also studies that look at the economic benefits of alternative cooling systems (Després and Adamovic, 2020), which find high benefits, but these tend to be focused on nuclear with river water abstraction (which is not relevant in the UK) or thermal plant (which are being phased out under Net Zero), however these technologies are suitable for biomass and CCS sites. For the new mix of energy generation for Net Zero, and especially for biofuel, biomass, CCS and hydrogen, the most obvious no regret option is for further analysis of the possible risks with respect to water demand of new generation plant, the number required, and the linkages with Risk I8 on water supply. These factors could lead to important adaptation options around siting and technology options, and at the very least, the cost implications for any water use under a changing climate. | G30: England | H30: Low | I30: Medium | J30: Medium | K30: Medium | L30: High | M30: Partially | N30: Further investigation | O30: Further Investigation | P30: High (8) | Q30: Medium (Amber) | R30: High (Net Zero) | W30: Y
A31: I10 | B31: I10 Risks to energy from high and low temperatures, high winds, lightning | C31: Yes | D31: 4 | E31: There are benefits of additional action in the next five years. For example, further investigation on the implications of increased vegetation growth rates and the future risks of damage from falling trees. The potential for greater use of ‘soft’ adaptation solutions is identified in NGG’s ARP2 report (the specific idea mentioned being changes to working practices). Although organisations are generally already exploring this concept, it is an area where collaboration between companies and between sectors could further facilitate progress in adaptation. There could be benefits in exploring this further through existing collaborative channels. Metz et al. (2016) indicate there are benefits from incorporating climate change information into the decision-making stages regarding the design of new assets and life extension of existing assets. This activity would reduce the potential for lock-in. A watching brief on the evidence regarding future wind speeds could be considered, to be reviewed if evidence suggests an increase in maximum wind speeds of 5% or more are indicated. Further investigation on activities being implemented by the energy sector on existing plans to protect assets from increased lightning strikes is needed to assess whether this should be included as an action here. There are no regret options involved in better understanding of the potential influence of climate on future energy demand, and thus the Net Zero strategies (see H6), as these influence energy supply. | F31: There is emerging information on the costs and benefits of climate smart design of energy generation including renewables. There is less evidence on the risk levels and potential costs and benefits of climate smart design for the new generation of technologies that will be developed to meet Net Zero, though there are obvious early low regret actions to further investigate these. There are several hazards and a number of different energy generation technologies within this risk, each of which has particular adaptation responses. The risk of wind damage to energy supply and transmission infrastructure is one area, and there may be compounding effects from increased vegetation growth. There has been some analysis of these aspects, and the potential increase in vegetation management costs, which can be considered as an impact or an adaptation) (Metroeconomica, 2004), though there are additional options, e.g. wind fences/breaks, circuit breakers, etc. The potential changes in wind regimes and wind power generation are highlighted as a watching brief above: there are technical design as well as operational management options to address potential changes should these emerge. There is a more general approach for adaptation, with the inclusion of climate risk assessment as part of project design and financial and economic appraisal (see also the Green Book Supplementary Guidance on Accounting for Climate Change, Defra, 2020a). However, there is less evidence on the risk levels and potential costs and benefits of climate smart design for the new generation of technologies that will be developed to meet net zero: an obvious early low regret action is to further investigate these. | G31: England | H31: High | I31: High | J31: High | K31: High | L31: High | M31: Partially | N31: Further investigation | O31: Further Investigation | P31: High(8) | Q31: Medium (Amber) | R31: High (Net Zero) | W31: Y
A32: I11 | B32: I11 Risks to offshore infrastructure from storms and high waves | C32: Yes | D32: 4 | E32: 4.12.3.1 Additional planned adaptation that would address the adaptation shortfall (I11) Adaptations are outlined in Step 1 and include changes to the design loads, extreme wave elevation and accessibility of offshore infrastructure for maintenance and crew transfer. In some regions these changes represent a rise in risk, and in others the net effect may be a reduction (i.e. a reduction in wave height counteracting the rise in sea level). Also, the expected changes in average annual energy production per unit of installed capacity by 2100 are comparable to the existing year-to-year variability. All these forecasts are predicated on the projected effects of climate change on the marine environment, for which there is currently low confidence. Given the anticipated expansion of offshore renewable energy in order to meet Net Zero and current low confidence in marine projections, further investigation into the potential changes in relevant climate metrics including wind and wave heights could better inform design and siting choices. | F32: This risk is evaluated as Sustain current action. As with the previous risks, the potential changes in the offshore wind regime and implications for offshore energy infrastructure (notably offshore wind), as well as other offshore risks (e.g. wave regimes), requires periodic review (e.g. Stewart et al., 2014), but there are technical designs for turbines as well as operational management options to address potential changes should these emerge, and a general recommendation on the use of climate risk assessment in new project design and appraisal. Offshore, subsea cable failures are currently the most important failure risk; these can occur from changes in tidal flows (Dinmohammadi et al., 2019) and might warrant further consideration of risks. | G32: England | H32: Low | I32: Medium | J32: Medium | K32: Medium | L32: Medium | M32: Yes | N32: Sustain current action | O32: Sustain current action | P32: High (8) | Q32: Medium (Amber) | R32: High (Net Zero) | W32: Y
A33: I12 | B33: I12 Risks to transport from high and low temperatures, high winds, lightning | C33: No | D33: 4 | E33: 4.13.3.1. Additional planned adaptation that would address the adaptation shortfall (12)? In a study on the influence of uncertain asset stock data on the assessment of climate risks for railways in Great Britain, Dikanski et al. (2018) found that avoidable uncertainty in basic asset data (in this case related to bridge scour), can outweigh uncertainty in climate projections by an order of magnitude. They identify better asset information collection by infrastructure managers as a quick win for effect climate adaptation. Heat-related rail buckling (and other heat-related asset failures) is a clear risk to future rail operations. CCC (2019) report that planned levels of future activity are appropriate and should continue to be implemented to ensure risk is managed. Moreover, the CCC report that actions being taken to reduce risk by the rail industry are likely reducing vulnerability in some areas, but evidence is currently lacking. This may be due to the current indicators of resilience (delay data), which may not directly indicate how the physical vulnerability of assets is changing. The Tomorrow’s Railway and Climate Change Adaptation (TRaCCA) project (RSSB, 2016b) made a number of recommendations to Government including enhanced weather incident reporting and asset condition monitoring and revised standards (for instance, increasing the stress-free temperature of steel rail in line with future climate projections). The CCC (2019) observe that although Network Rail’s route plans contain relevant actions and consider a scenario of 4°C global warming by 2100, the strategy provides guidance to prepare for future action rather than specific measurable goals to reduce risk. For local roads, the CCC (2019) conclude that it is not clear whether there has been a systematic evaluation of climate change risks. Similarly, to rail, it is recommended that better indicators of climate resilience for roads are developed. For ports and airports, it is clear from the CCC (2019) report that lack of engagement with the ARP process may be a barrier to adaptation. Although 16 ports and airports submitted to ARP2, another six declined to participate. The CCC argue that without making the Adaptation Reporting Power mandatory, it is hard to be assured that risk is being managed in the sector as a whole. Similarly to road and rail, improved data on disruption to ports and airports would assist in assessing current and potential future risk. | F33: In general, there are a set of no regret options in the form of improved weather and climate services, including early warning systems, for extreme risks for transport, which have been found to have high benefit to cost ratios across modes from the avoided damage and thus value of information (Clements et al., 2013). There are further opportunities for these options, and general management of weather related risks through digital platforms, remote sensing, etc., and their use in real time network management (EEA, 2014), which can be considered no-regret because of the reduced costs of disruption and thus economic benefits in terms of travel time (ToPDAd, 2015). The potential risks of high temperatures on the rail networks, and the potential economic costs of rail buckling risks under climate change have been previously estimated in the UK (e.g. Dobney et al., 2009, Alvater et al., 2012). The reactive adaptation response to these has been speed restrictions, although these have important travel time costs. There has been some analysis of the cost-effectiveness of options to address these risks, though these are mostly focused on improved risk assessment and monitoring (RSSB, 2016). There are potential rising risks from wind and vegetation growth, which are likely to mean increased vegetation management costs (which can be considered an impact or an adaptation). There has also been analysis of the potential economic costs of heat on highways (including rutting and user delay costs, as well as additional capital maintenance costs) and the costs and benefits of addressing heat risks to highways (Atkins, 2013a). This considers technical surfacing options and found a modest positive net present value and cost-benefit ratio of slightly greater than 1. Alvater et al. (2012) also investigated the additional costs of using better asphalt for roads in the UK, and found the costs generally outweighed the benefits. There is also a large international literature in this area (from warmer countries), which highlight improved maintenance practices, risk assessments, early warning, and enhanced design standards for roads (e.g. EEA, 2014, Ecofys, 2016). There are other approaches, e.g. with greater redundancy in road networks, but these involve significant extra costs. There is also emerging focus on focusing adaptation investments on the vulnerability hot spots on networks, i.e. to identify the points on the system where greater resilience would be most cost-effective (as part of network level analysis rather than for individual assets). While this has mostly focused on flooding (Oh et al., 2020), the same approaches could apply to other risks. For existing infrastructure, improved monitoring and information, and also improvement of maintenance practices and operations, are considered low-regret adaptation options. For new infrastructure, there are opportunities for mainstreaming climate change adaptation into planning and design, to avoid retrofitting later. The balance of costs and benefits for such approaches depends on the costs, the timing and level of discounted future benefits, as well as the costs of retrofit later. This means some, but not all measures are likely to have positive NPVs and these may be site specific. There is the potential for decision making under uncertainty approaches for new transport infrastructure (e.g. considering flexibility, robustness, adaptive management) but these have important time and resource implications. The main risks of lock-in, and thus main role for such approaches, are for new roads, rail, etc. (rather than refurbishment or upgrades) due to siting decisions. | G33: England | H33: Medium | I33: High | J33: High | K33: High | L33: High | M33: Partially | N33: More action needed | O33: More action needed | P33: Medium (5) | Q33: High (Green) | R33: Low (no key policies in the next two years) | Y33: Y
A34: I13 | B34: I13 Risks to digital from high and low temperatures, high winds, lightning | C34: No | D34: 4 | E34: 4.14.3.1. Additional planned adaptation that would address the adaptation shortfall (I13) Further adaptation would include incorporating digital infrastructure into existing infrastructure climate adaptation plans recognising the criticality of ICT provision for wider infrastructure and society. Further information is also needed to identify and protect assets at risk of flooding and wildfires together with a better understanding of future impacts on radio communication VHF/UHF systems. | F34: While there is some information on adaptation options for the digital and ICT sector (Horrocks et al., 2010), there does not appear to be a large literature on the costs and benefits of adaptation. There is a general low regret option to ensure better information on such risks, as well as to ensure climate risk assessment is included in design (and financial and economic appraisal, see also the supplementary Green book Guidance on accounting for climate change, Defra, 2020a). It is noted that the sector typically has short design lifetimes, and thus there is the potential to consider the management of some risks (e.g. equipment) as part of upgrades rather than through designing for future climates. However, there may still be cost-effective actions for critical digital infrastructure, given the cost of downtime from failures is often high; evidence from companies that report that the cost of downtime could be as high as £thousands per minute (Ponemon Institute, 2016). Warmer temperatures are likely to mean higher cooling needs and associated energy costs (Lee et al., 2013; Capozzoli and Primiceri, 2015; Song et al., 2015). There are a range of adaptation options from early warning and emergency planning through to back-ups to address heat extremes. These issues are linked to the general increase in cooling demand (see Chapter 5: Kovats and Brisley, 2021) and the potential role for energy efficiency standards. The consideration of network risks, and more focused adaptation strategies to key vulnerabilities, can be a more efficient use of available adaptation resources. Adaptation can also be achieved by enhancing network redundancy and introducing back-ups. Pant et al. (2020) investigated the economic impacts of failure events in the telecoms network and estimated that direct losses for the top 50 events could vary between £220,000–£3.6 million/day and total losses vary between £0.34–£7.0 million/day. However, as the degrees of connections are increased, the economic impacts were found to decrease. The authors also show the benefits of introducing backup supply for the electricity sector in delaying and thereby decreasing the disruptions in the ICT sector by up to ~90% compared to a scenario with one connection and no back up (though note the study does not assess costs, and thus the overall economic net benefit). It is also highlighted that ICT and digital solutions can help reduce risks or realise opportunities in other sectors, i.e. they have considerable potential as part of adaptation across many areas (ITU, 2014). | G34: England | H34: Low | I34: Medium | J34: Medium | K34: Medium | L34: Medium | M34: No | N34: Further investigation | O34: Further Investigation | P34: Low (2) | Q34: Low (Red) | R34: Low (no key policies in the next two years) | X34: Y
A35: ID01 | B35: ID1 Risks to UK food availability, safety, and quality from climate change overseas | C35: Yes | D35: 7 | E35: COVID-19, as a systemic shock that has critically impacted on food systems, and an exemplar of some of the climate-related risks that may occur in future, highlights the need to consider food-system resilience as a guiding principle. This is recognised by Henry Dimbleby and the National Food Strategy’s (NFS) first report (Dimbleby, 2020): ‘There is a lot of work to do if we are to rebuild a food system that delivers safe, healthy, affordable food to everyone; that is a thriving contributor to our urban and rural economies; that restores and enhances the natural environment for the next generation; that is built upon a resilient, sustainable and humane agriculture sector; and that is robust in the face of future crises.’ (Dimbleby, 2020, National Food Strategy Part One, P.17, emphasis ours) In particular, there is a need (as acknowledged in the NFS part 1) that due consideration given to a range of aspects within emerging Free Trade Agreements, post EU-Exit. As highlighted in a Chatham House report (Benton et al., 2019), lack of consideration of potential environmental governance and exposure to climate risks could undermine the ability to have a resilient food system as climate risks mount. In addition, there is the potential for a reduction in UK agricultural resilience if lowering of production standards became necessary to compete with cheaper imports. Finally, FTAs through affecting prices and price resilience have potential impacts on UK food insecurity, especially for the marginalised groups, as noted in NFS. A recent CCC outcomes study (Watkiss et al., 2019) suggested that the Government could play a role in removing some of the barriers for the private sector to encourage climate change adaptation. Simultaneously, this private sector support could ensure a higher level of resilience along supply chains. Since many supply chains have international dimensions, a multi-national regulatory structure in the food commodity markets, which are most vulnerable to climate-related supply-side shocks, could play a beneficial role. Further development and uptake of insurance instruments that protect both domestic and international actors in food supply chains would also contribute to adaptation. A greater focus on adaptive management, research, and learning in this sector would contribute to a more resilient food system. For example, identifying regions/countries which already show vulnerability to weather events, food production, and transport disruptions, and understanding how these vulnerabilities might change under different climate scenarios. This would help to understand the scale of the future vulnerability of the UK market and provide a stronger rationale for action (Watkiss et al., 2019). Populations at highest risk of lack of economic access to food are concurrent with those at risk of obesity and malnutrition (Drewnowski, 2012; Jones et al., 2014b, Food Foundation 2017). Therefore, addressing food access inequality, access to fresh produce, and informed dietary choices, will likely have the co-benefit of reducing vulnerability to the risk of decreasing nutritional quality of food produced due to climate change. | F35: There are some aspects of climate change risks and responses that have been quantified for food supply chain resilience, but there is little information on the associated costs and benefits (in aggregate). Watkiss et al., (2019) for the CCC reviewed the available options and provided some qualitative analysis of possible costs and benefits. This indicates a range of low-regret options, as well as some additional options to start the process for planning for these risks. | G35: UK | H35: High | I35: High | J35: High | K35: High | L35: High | M35: Partially | N35: More action needed | O35: More action needed | P35: N/A | Q35: N/A | R35: Medium (new food security strategies) | U35: Y
A36: ID02 | B36: ID2 Opportunities for UK food availability and exports from climate impacts overseas | C36: No | D36: 7 | E36: N/A | F36: As reviewed in section 7.4.2, ensuring access to a broad range of international markets would capitalise on any opportunities associated with climate impacts overseas. There is no evidence to suggest further actions that would support such opportunities. Access to markets, which was covered in some detail in CCRA2 Chapter 7, has the co-benefit of providing some resilience to external shocks, be they climate-induced, or sourced elsewhere (e.g., a global health disruption such as COVID-19). Hence there are multiple lines of reasoning that suggest benefits of access to markets. | G36: UK | H36: Low | I36: Low | J36: Low | K36: Low | L36: Low | M36: Yes | N36: Watching brief | O36: Watching brief | P36: N/A | Q36: N/A | R36: Low (No key policies looking at opportunities in the next two years) | U36: Y
A37: ID03 | B37: ID3 Risks and opportunities to the UK from climate-related international human mobility | C37: No | D37: 7 | E37: N/A | F37: Any adaptation in the next five years would most likely involve protecting the human security of people on the move, and those in low-income receiving areas in the Global South, rather than on the national security of the UK. Solutions lie in creating safe pathways for migration, the movement of people transmission pathway, and helping the UK and other host countries to accommodate newcomers through education and language courses, training and retraining in skills relevant to the job market, planning for infrastructure and services in areas likely to receive migrants, as well as managing public perception of migration. Migration as an adaptive response, and a proportion of the population outside their places of origin, are constants of any society. Thus, opportunities lie in recognising the agency of migration and the novel forms of organisation and cooperation that emerge within migrant groups that have the potential to benefit the UK and its overseas interests (Papadopoulos & Tsianos, 2013; Stierl, 2018). The Foresight report in 2011 (Foresight & Government Office for Science, 2011) highlighted the potential benefit to all nations of supporting safe and orderly migration that maintains the dignity of the migrant. In the context of the Lifetime Skills Guarantee the UK Prime Minister has highlighted skilled labour shortages, that could be filled with migration until filled domestically. Thus, there is an opportunity for the UK to set up procedures to ensure that any increases in migration are beneficial to the nation. Second, there are win-win opportunities ensuring that overseas development and humanitarian response empowers local communities such that they are not forced to migrate but have agency in if, when, and where they chose to move. The Foresight follow-up report noted that different Government Departments were responding quite differently, thus there is the opportunity to create greater cohesion between departments. While there are several Cabinet committees dedicated to considering both domestic and international issues, it appears that the membership of some of these committees could be more strategically focussed to tackle the linkages between climate and migration. For example, the overarching National Security Council chaired by the Prime Minister which inter alia considers ‘international relations and development’ included both the Home office and DFID (now FCDO). The Climate Action Implementation Committee included DFID but not the Home Office, while the Committee on Climate Action Strategy included neither DFID nor the Home office. During the period immediately following the UK’s exit from the European Union there is a window of opportunity to provide pathways for safe and orderly migration to the UK. Migration decisions and migration flows are already mixed, and so climate migrants will come to the UK, not as a separate, easily defined group, but as economic migrants or potentially as asylum seekers. The UK can maximise the benefits that any new migrants bring and thus there are obvious benefits to the UK’s investment in social mechanisms that allow newcomers to integrate effectively into the job market and local society. The merger of DFID and the Foreign and Commonwealth Office (FCO) as FCDO, can provide an opportunity to develop more deliberate climate and migration policies with oversight from the most senior Cabinet Committees. Monetised indicative costs and benefits of additional adaptation are not currently available at the time of writing. | G37: UK | H37: Low | I37: Low | J37: Low | K37: Medium | L37: Medium | M37: Partially | N37: Watching brief | O37: Watching brief | P37: N/A | Q37: N/A | R37: Low (no key policies in the next two years) | AG37: N
A38: ID04 | B38: ID4 Risks to the UK from international violent conflict resulting from climate change on the UK | C38: No | D38: 7 | E38: N/A | F38: As noted by Smith et al. (2018a), in the context of risks to US international assistance, “the impacts of climate change, variability, and extreme events can slow or reverse social and economic progress in developing countries, thus undermining international aid and investments made by the United States and increasing the need for humanitarian assistance and disaster relief.” A similar observation could be made regarding the overseas aid budget of the UK. For mitigation of water-based conflict, more cooperative behaviour is associated with transboundary agreements (Munia et al., 2016) when participating countries are governed by treaties with water allocation mechanisms that allow flexibility and specificity. Therefore, there may also be opportunities to reduce current tensions through appropriately deployed international agreements on shared resources including access to water (where rivers run between countries) or new opportunities in areas such as the Arctic. The evidence for additional benefits from proactive engagement in reducing local tensions in regions more prone to conflict through infrastructure investment and setting up local or transboundary agreements which can underpin more cooperative behaviour between different stakeholders is increasing (for example, Munia et al., 2016). The main cost associated with this is a more strategic and systems approach to investing international aid aligned to climate change adaptation associated with conflict prevention. | G38: UK | H38: Low | I38: Medium | J38: Medium | K38: Medium | L38: High | M38: Partially | N38: More action needed | O38: More action needed | P38: N/A | Q38: N/A | R38: Low (No key policies looking or opportunities ac the next two years) | AG38: N
A39: ID05 | B39: ID5 Risks to international law and governance from climate change overseas that will impact the UK | C39: No | D39: 7 | E39: N/A | F39: Diplomacy is the main means of adaptation in relation to this risk. Further engagement with multilateral processes and institutions would have benefits for ensuring that the UK preserves its interests and strengthens its image as a respected multilateral player. This could include engaging constructively with a multiplicity of processes and initiatives in the context of climate change, such as inter alia by supporting the work of the International Law Commission on sea-level rise in relation to international law started in 2019, the work of the UNFCCC on loss and damage (including its Task Force on Displacement) and the on-going modernisation of the Energy Charter Treaty. There would also be benefits from producing a clear plan to meet the challenges posed by a shift in UK relationships with traditional allies and changing dynamics at the UN, to coordinate its activities with the EU, and to build new partnerships with inter alia the Commonwealth. Whilst the short-term benefit of these adaptations is small, it rises on longer timescales, commensurate with the increase in risk magnitude. Planning is needed now in order to enable adaptation in the future. | G39: UK | H39: Low | I39: Medium | J39: High | K39: High | L39: High | M39: Partially | N39: More action needed | O39: More action needed | P39: N/A | Q39: N/A | R39: Low (no key policies in the next two years) | AG39: N
A40: ID06 | B40: ID6 Opportunities from climate change (including arctic ice melt) on international trade routes | C40: No | D40: 7 | E40: N/A | F40: There is some projected analysis (e.g., Bekkers et al., 2016) which indicates that opportunities from climate change (including Arctic ice melt) on international trade routes could be large including from the economic effects of trade that is facilitated by a reduction in transport distance between suppliers and consumers. The effect on UK GDP was estimated to be equivalent to an annual increase of 0.24%, although this was associated with year-round (not just summer) transport access. There are also potential tourism opportunities that increased access to the Arctic allows, and associated port development in locations that facilitate these trade and tourism opportunities. While these would need to be seen against potentially very large negative impacts from an ice-free Arctic for other reasons (e.g., loss of or damage to arctic ecosystems, potential higher global warming levels, impacts on European weather, etc.) they do indicate potential economic benefits. There is an issue whether these benefits will be fully realised by non-government adaptation alone, and it is likely that higher benefits could be achieved for the UK (as compared to competitor coastal countries) through some enabling actions from government, which would have likely low costs. | G40: UK | H40: Low | I40: High | J40: High | K40: High | L40: High | M40: Yes | N40: Watching brief | O40: Watching brief | P40: N/A | Q40: N/A | R40: Low (no key policies in the next two years) | U40: Y
A41: ID07 | B41: ID7 Risks from climate change on international trade routes | C41: Yes | D41: 7 | E41: N/A | F41: The resilience of trade to shocks first became an area of focus following the 2007/8 and 2010/11 food-price spikes (Challinor et al., 2016; Challinor et al., 2018), and, of course, COVID-19 has highlighted the vulnerabilities inherent in the trade in some goods. Given that shocks are likely to increase in the future, as climate hazards from extreme events increase, there is benefit from a focus on building further resilience. However, resilience would typically arise from four main properties: building in redundancy (e.g., stocks), diversity (of sourcing, or substitutability), creating modularity or distributed rather than centralised networks, and creating greater flexibility/adaptability. All of these properties have typically been removed to increase efficiency and the leanness of supply chains. Thus, there is a trade-off between fragility (and lower prices) and resilience (and higher prices). As risks increase, the trade-off tips towards resilience providing better returns on average. Resilience as a ‘design feature’ may become a greater focus for investment during post-COVID recovery. | G41: UK | H41: Medium | I41: Medium | J41: High | K41: Medium | L41: High | M41: Partially | N41: More action needed | O41: More action needed | P41: N/A | Q41: N/A | R41: Medium (TCFD reporting) | U41: Y
A42: ID08 | B42: ID8 Risk to the UK finance sector from climate change overseas | C42: Yes | D42: 7 | E42: There have been significant shifts in assessing, disclosing, and analysing climate risks and more is expected in light of expected shifts from voluntary to mandatory action driven by regulators. While it is clear that the extent of physical risks is currently low and expected to become significant in the longer-term, there are clear dangers in considering physical risks ‘as under control’. There are lock-ins especially within real-estate investment where adaptation measures require further investment. Whilst there has been improvement in adaptation action from CCRA2, changes have mainly been made in climate risk regulation and reporting as opposed to changing capital flows. Moreover, given the tightening climate policy landscape, there are significant lock-in effects if there is no substantial redirection of financial flows. Whilst banking and insurance sectors have responded effectively to current extreme weather events, the increase in magnitude and frequency means the likelihood of ‘unhedgeable risk’ is higher – straining the insurance sector. Given that financial risks are still not integrated within firm operating models or in financial markets as a whole, there are still significant systematic risks (Mandel et al., 2020). Whilst companies have started adopting TCFD recommendations, identifying climate risks is only the first step. TCFD’s most recent status update report acknowledges that there needs to be a better understanding of how disclosing climate-related financial information is changing corporate strategies on adaptation, and how investors are using the disclosed information to inform their decisions (TCFD, 2017). The UK has been seen as a leading power through the passing of the 2008 Climate Change Act, the recent adoption of a Net Zero target, as well as institution building and coordination across government – though less so on climate change adaptation (CCC, 2019). With the UK set to host the 26th Conference of the Parties of the UNFCCC (COP26), there is also an aspect of this risk about showing leadership on managing the risks to finance from climate change. A critical issue to tackle at COP26 is the existence of a global green finance gap and many in the finance sector highlight the uncertainty over national and international climate policy as a key factor in this gap (Hafner et al., 2020). | F42: It is difficult to estimate the potential costs and benefits of further adaptation. However, what is clear is that the potential risks to the financial markets in the UK from climate change are extremely large, and because of the role of UK financial services, very large for the UK. Dietz et al. 2016, using a Monte Carlo simulation of the DICE model, estimated the present value at risk as a result of climate change under a business-as-usual pathway to global financial assets as $2.5 trillion (mean expected losses, discounted in present value terms) between now and the end of the century, and still $1.7 trillion under a 2°C pathway. However, under business as usual, the 99th percentile tail risk is $24.2 trillion. A sizeable amount of global financial assets are managed by the UK financial markets. There are existing voluntary initiatives (TCFD) that are helping to increase the disclosure of these potential risks, but as highlighted in Chapter 6 (Surminski, 2021), there appears to be less action on adaptation. | G42: UK | H42: Low | I42: Medium | J42: Medium | K42: Medium | L42: High | M42: Partially | N42: Sustain current action | O42: Sustain current action | P42: N/A | Q42: N/A | R42: Medium (TCFD reporting) | AE42: Y
A43: ID09 | B43: ID9 Risk to UK public health from climate change overseas | C43: No | D43: 7 | E43: N/A | F43: Actions to promote adaptation to emerging diseases include: ● More real-time monitoring of air travel routes, transmission pathways of movement of people and goods. ● Communicate outdoor risks if a vector-borne disease is introduced. ● Improve training and awareness of primary health care practitioners. ● Raise the levels of surveillance programmes and some random screening (for example, part of blood donation screening for antibodies). ● Improvement of public and professional level information, transmission pathway IT/information. There would be benefits from increased surveillance of wildlife, people or other imports (e.g., used tyres) coming into the UK, which comes with increased costs. However, if newly arrived infected vectors or animals in combination with a more favourable UK climate leads to local transmission, the cost of the impacts may be a lot more. COVID-19 has provided a good example of the scale of impact costs and how this can cascade into other sectors. Therefore, it shows that investments in surveillance can pay off to avoid high impact situations. It is not clear how the UK could fully protect itself from risks from emerging diseases overseas that have a transmission pathway to the UK. Targeted public information, advertisements in holiday destinations about outbreaks, and more information or advertisements in in-flight magazines would support this effort. Further actions include improving seasonal forecasts of conditions for the establishment of vector-borne disease, especially the extension of summer-like conditions into the autumn; improved awareness of risks at both primary and secondary health care; better monitoring and surveillance of potential vectors in the UK, especially for virus antibodies. Actions can also be taken that target key overseas areas, i.e., monitoring and research in areas overseas that are likely to be prone to the emergence of new infectious diseases both vector-borne and other contagious diseases. Ongoing collaborative research and monitoring are critical if imported health risks are to be avoided. One key challenge for research comes from EU Exit: in the past, the European Commission funded many of these integrated projects involving environmental and social controls and impacts of infectious diseases. If this funding source becomes closed to the UK, then these opportunities will need to be replaced by UK funding if we are to continue to engage in this pool of expertise and knowledge production. | G43: UK | H43: High | I43: High | J43: High | K43: High | L43: High | M43: Partially | N43: More action needed | O43: More action needed | P43: N/A | Q43: N/A | R43: Medium (reviews of disease planning may emerge post-Covid, but uncertain) | AG43: N
